[{"created_at":"Tue Jun 25 15:35:35 +0000 2013","id":349551454618525697,"id_str":"349551454618525697","text":"RT @ruanji: \u795d\u798fRT @ziliyang: \u5929\u5b89\u95e8\u6bcd\u4eb2\u4e01\u5b50\u9716\u5973\u58eb\u7684\u5148\u751f\u848b\u57f9\u5764\u8001\u5e08\u4ece6\u67089\u65e5\u81f3\u4eca\u4e00\u76f4\u5728\u4f4f\u9662\uff0c\u67e5\u51fa\u6765\u524d\u5217\u817a\u764c\uff0c\u6b63\u8981\u624b\u672f\u3002\u867d\u7136\u4ed6\u5f88\u4e50\u89c2\uff0c\u4f46\u6bd5\u7adf\u662f70\u591a\u5c81\u7684\u4eba\u4e86\uff0c\u60a3\u4e0a\u764c\u75c7\u4ee4\u4eba\u62c5\u5fe7\u3002\u4e01\u5b50\u9716\u848b\u57f9\u5764\u4e24\u4f4d\u524d\u8f88\u8001\u6765\u76f8\u6fe1\u4ee5\u6cab\uff0c\u5e0c\u671b\u4ed6\u4eec\u80fd\u770b\u5230\u572864\u6b92\u547d\u7684\u513f\u5b50\u7ec8\u4e8e\u662d\u96ea\u90a3\u4e00\u5929\u2026","source":"\u003ca href=\"http:\/\/google.com\" rel=\"nofollow\"\u003enewmyteabot27\u003c\/a\u003e","truncated":false,"in_reply_to_status_id":null,"in_reply_to_status_id_str":null,"in_reply_to_user_id":null,"in_reply_to_user_id_str":null,"in_reply_to_screen_name":null,"user":{"id":267502889,"id_str":"267502889","name":"\u4e2d\u6587\u70ed\u63a8\u673a\u5668\u4eba","screen_name":"iruitui","location":"\u8be5\u5730\u5740\u65e0\u6cd5\u663e\u793a","description":"\u5bfb\u627e\u5e76\u8f6c\u53d1\u70ed\u95e8\u6216\u6709\u8da3\u7684\u63a8\u6587\u3002\r\n\r\n\u6240\u8f6c\u53d1\u63a8\u6587\u5e76\u4e0d\u8868\u660e\u672c\u5e10\u53f7\u7ef4\u62a4\u8005\u89c2\u70b9\u3002\u63a8\u6587\u7684\u771f\u4f2a\u4e0e\u5bf9\u9519\u8bf7\u81ea\u884c\u5224\u65ad\u3002\r\n\r\n\u5982\u6709\u88ab\u672c\u63a8\u8f6c\u53d1\u7684\u63a8\u6587\u9700\u8981\u5220\u9664\uff0c\u8bf7\u77e5\u6089 @iruitui\u3002","url":"https:\/\/t.co\/OTUFpm2Idf","entities":{"url":{"urls":[{"url":"https:\/\/t.co\/OTUFpm2Idf","expanded_url":"https:\/\/www.google.com\/ncr","display_url":"google.com\/ncr","indices":[0,23]}]},"description":{"urls":[]}},"protected":false,"followers_count":3367,"friends_count":1,"listed_count":111,"created_at":"Thu Mar 17 01:57:12 +0000 2011","favourites_count":30,"utc_offset":-32400,"time_zone":"Alaska","geo_enabled":false,"verified":false,"statuses_count":98811,"lang":"zh-cn","contributors_enabled":false,"is_translator":false,"profile_background_color":"C0DEED","profile_background_image_url":"http:\/\/a0.twimg.com\/images\/themes\/theme1\/bg.png","profile_background_image_url_https":"https:\/\/si0.twimg.com\/images\/themes\/theme1\/bg.png","profile_background_tile":false,"profile_image_url":"http:\/\/a0.twimg.com\/profile_images\/2830387364\/ab16e3458fd9dec64a098b1e8c1a26f6_normal.png","profile_image_url_https":"https:\/\/si0.twimg.com\/profile_images\/2830387364\/ab16e3458fd9dec64a098b1e8c1a26f6_normal.png","profile_link_color":"0084B4","profile_sidebar_border_color":"C0DEED","profile_sidebar_fill_color":"DDEEF6","profile_text_color":"333333","profile_use_background_image":true,"default_profile":true,"default_profile_image":false,"following":true,"follow_request_sent":null,"notifications":null},"geo":null,"coordinates":null,"place":null,"contributors":null,"retweeted_status":{"created_at":"Tue Jun 25 15:17:46 +0000 2013","id":349546970303569920,"id_str":"349546970303569920","text":"\u795d\u798fRT @ziliyang: \u5929\u5b89\u95e8\u6bcd\u4eb2\u4e01\u5b50\u9716\u5973\u58eb\u7684\u5148\u751f\u848b\u57f9\u5764\u8001\u5e08\u4ece6\u67089\u65e5\u81f3\u4eca\u4e00\u76f4\u5728\u4f4f\u9662\uff0c\u67e5\u51fa\u6765\u524d\u5217\u817a\u764c\uff0c\u6b63\u8981\u624b\u672f\u3002\u867d\u7136\u4ed6\u5f88\u4e50\u89c2\uff0c\u4f46\u6bd5\u7adf\u662f70\u591a\u5c81\u7684\u4eba\u4e86\uff0c\u60a3\u4e0a\u764c\u75c7\u4ee4\u4eba\u62c5\u5fe7\u3002\u4e01\u5b50\u9716\u848b\u57f9\u5764\u4e24\u4f4d\u524d\u8f88\u8001\u6765\u76f8\u6fe1\u4ee5\u6cab\uff0c\u5e0c\u671b\u4ed6\u4eec\u80fd\u770b\u5230\u572864\u6b92\u547d\u7684\u513f\u5b50\u7ec8\u4e8e\u662d\u96ea\u90a3\u4e00\u5929\u3002\"","source":"\u003ca href=\"http:\/\/twitter.com\/download\/android\" rel=\"nofollow\"\u003eTwitter for Android\u003c\/a\u003e","truncated":false,"in_reply_to_status_id":null,"in_reply_to_status_id_str":null,"in_reply_to_user_id":null,"in_reply_to_user_id_str":null,"in_reply_to_screen_name":null,"user":{"id":44390717,"id_str":"44390717","name":"\u5409\u8f6f\u7cd6","screen_name":"ruanji","location":"\u5730\u7403","description":"\u65b0\u7684\u5e0c\u671b\u5728\u5170\u5929","url":"http:\/\/t.co\/3DwvRlVArP","entities":{"url":{"urls":[{"url":"http:\/\/t.co\/3DwvRlVArP","expanded_url":"http:\/\/jiblog.jiruan.net","display_url":"jiblog.jiruan.net","indices":[0,22]}]},"description":{"urls":[]}},"protected":false,"followers_count":7171,"friends_count":1058,"listed_count":156,"created_at":"Wed Jun 03 16:13:35 +0000 2009","favourites_count":7075,"utc_offset":36000,"time_zone":"Sydney","geo_enabled":true,"verified":false,"statuses_count":34452,"lang":"en","contributors_enabled":false,"is_translator":false,"profile_background_color":"8B542B","profile_background_image_url":"http:\/\/a0.twimg.com\/images\/themes\/theme8\/bg.gif","profile_background_image_url_https":"https:\/\/si0.twimg.com\/images\/themes\/theme8\/bg.gif","profile_background_tile":false,"profile_image_url":"http:\/\/a0.twimg.com\/profile_images\/3648674344\/e1e65823c59bef067f981b2a2e3183b3_normal.jpeg","profile_image_url_https":"https:\/\/si0.twimg.com\/profile_images\/3648674344\/e1e65823c59bef067f981b2a2e3183b3_normal.jpeg","profile_banner_url":"https:\/\/pbs.twimg.com\/profile_banners\/44390717\/1368346739","profile_link_color":"9D582E","profile_sidebar_border_color":"D9B17E","profile_sidebar_fill_color":"EADEAA","profile_text_color":"333333","profile_use_background_image":true,"default_profile":false,"default_profile_image":false,"following":null,"follow_request_sent":null,"notifications":null},"geo":null,"coordinates":null,"place":null,"contributors":null,"retweet_count":4,"favorite_count":0,"entities":{"hashtags":[],"symbols":[],"urls":[],"user_mentions":[{"screen_name":"ziliyang","name":"\u6768\u5b50\u7acb","id":101700770,"id_str":"101700770","indices":[5,14]}]},"favorited":false,"retweeted":false,"lang":"zh"},"retweet_count":4,"favorite_count":0,"entities":{"hashtags":[],"symbols":[],"urls":[],"user_mentions":[{"screen_name":"ruanji","name":"\u5409\u8f6f\u7cd6","id":44390717,"id_str":"44390717","indices":[3,10]},{"screen_name":"ziliyang","name":"\u6768\u5b50\u7acb","id":101700770,"id_str":"101700770","indices":[17,26]}]},"favorited":false,"retweeted":false,"lang":"zh"},{"created_at":"Tue Jun 25 15:34:54 +0000 2013","id":349551282790465537,"id_str":"349551282790465537","text":"RT @yong___2: @BoAtheKOREA \nBoA - Tail of Hope \uac00\uc0ac\ubc88\uc5ed(\ub3c5\uc74c+\ub73b) \u521d\u3081\u3066\u6b69\u3044\u305f\u77e5\u3089\u306a\u3044\u9053\u306e\u4e0a \ud558\uc9c0\uba54\ub5bc \uc544\ub8e8\uc774\ud0c0 \uc2dc\ub77c\ub098\uc774 \ubbf8\uce58\ub178 \uc6b0\uc5d0 \ucc98\uc74c \uac78\uc5b4\ubcf8 \ubaa8\ub974\ub294 \uae38 \uc704 \u84bc\u3044\u98a8 \u65b0\u7dd1\u3092\u304f\u3059\u3050\u308a(cont) http:\/\/t.co\/\u2026","source":"\u003ca href=\"http:\/\/www.tweetdeck.com\" rel=\"nofollow\"\u003eTweetDeck\u003c\/a\u003e","truncated":false,"in_reply_to_status_id":null,"in_reply_to_status_id_str":null,"in_reply_to_user_id":null,"in_reply_to_user_id_str":null,"in_reply_to_screen_name":null,"user":{"id":345776117,"id_str":"345776117","name":"BoA the KOREA \ubcf4\uc544","screen_name":"BoAtheKOREA","location":"Korea","description":"\ubcf4\uc544\ub354\ucf54\ub9ac\uc544(BoAtheKOREA)  \u25cf \uac00\uc218 \ubcf4\uc544 ( @BoAkwon )\ub2d8\uc5d0 \uad00\ud55c \ubaa8\ub4e0 \uc815\ubcf4\ub97c \ud55c\uad6d\uc5b4\ub85c \uc81c\uacf5\ud569\ub2c8\ub2e4","url":null,"entities":{"description":{"urls":[]}},"protected":false,"followers_count":7422,"friends_count":596,"listed_count":67,"created_at":"Sun Jul 31 04:36:46 +0000 2011","favourites_count":1024,"utc_offset":32400,"time_zone":"Seoul","geo_enabled":false,"verified":false,"statuses_count":7688,"lang":"ko","contributors_enabled":false,"is_translator":false,"profile_background_color":"C0DEED","profile_background_image_url":"http:\/\/a0.twimg.com\/profile_background_images\/645819141\/ycz1u82yqr54i0v1g20a.jpeg","profile_background_image_url_https":"https:\/\/si0.twimg.com\/profile_background_images\/645819141\/ycz1u82yqr54i0v1g20a.jpeg","profile_background_tile":false,"profile_image_url":"http:\/\/a0.twimg.com\/profile_images\/2552492290\/ge3nbql5iz9tm74wizsh_normal.jpeg","profile_image_url_https":"https:\/\/si0.twimg.com\/profile_images\/2552492290\/ge3nbql5iz9tm74wizsh_normal.jpeg","profile_link_color":"0084B4","profile_sidebar_border_color":"C0DEED","profile_sidebar_fill_color":"DDEEF6","profile_text_color":"333333","profile_use_background_image":true,"default_profile":false,"default_profile_image":false,"following":true,"follow_request_sent":null,"notifications":null},"geo":null,"coordinates":null,"place":null,"contributors":null,"retweeted_status":{"created_at":"Tue Jun 25 13:17:25 +0000 2013","id":349516681451810818,"id_str":"349516681451810818","text":"@BoAtheKOREA \nBoA - Tail of Hope \uac00\uc0ac\ubc88\uc5ed(\ub3c5\uc74c+\ub73b) \u521d\u3081\u3066\u6b69\u3044\u305f\u77e5\u3089\u306a\u3044\u9053\u306e\u4e0a \ud558\uc9c0\uba54\ub5bc \uc544\ub8e8\uc774\ud0c0 \uc2dc\ub77c\ub098\uc774 \ubbf8\uce58\ub178 \uc6b0\uc5d0 \ucc98\uc74c \uac78\uc5b4\ubcf8 \ubaa8\ub974\ub294 \uae38 \uc704 \u84bc\u3044\u98a8 \u65b0\u7dd1\u3092\u304f\u3059\u3050\u308a(cont) http:\/\/t.co\/YIHdEXcNsr","source":"\u003ca href=\"http:\/\/twitter.com\/download\/iphone\" rel=\"nofollow\"\u003eTwitter for iPhone\u003c\/a\u003e","truncated":false,"in_reply_to_status_id":null,"in_reply_to_status_id_str":null,"in_reply_to_user_id":345776117,"in_reply_to_user_id_str":"345776117","in_reply_to_screen_name":"BoAtheKOREA","user":{"id":126846235,"id_str":"126846235","name":"\uc6a9\uc774\/\u3088\u3093\u3088\u3093","screen_name":"yong___2","location":"TIFF's world \u26653\u2665","description":"Korean. but now in Tokyo. \uc598\ub4e4\uc544 \ub3c4\ucfc4\uc880 \uc62c\ub798...?","url":null,"entities":{"description":{"urls":[]}},"protected":false,"followers_count":1191,"friends_count":277,"listed_count":11,"created_at":"Sat Mar 27 05:00:09 +0000 2010","favourites_count":1639,"utc_offset":32400,"time_zone":"Seoul","geo_enabled":true,"verified":false,"statuses_count":69943,"lang":"ko","contributors_enabled":false,"is_translator":false,"profile_background_color":"FFF04D","profile_background_image_url":"http:\/\/a0.twimg.com\/images\/themes\/theme19\/bg.gif","profile_background_image_url_https":"https:\/\/si0.twimg.com\/images\/themes\/theme19\/bg.gif","profile_background_tile":false,"profile_image_url":"http:\/\/a0.twimg.com\/profile_images\/378800000044396650\/d9121c8f23efbfb81a657855ba375f41_normal.jpeg","profile_image_url_https":"https:\/\/si0.twimg.com\/profile_images\/378800000044396650\/d9121c8f23efbfb81a657855ba375f41_normal.jpeg","profile_banner_url":"https:\/\/pbs.twimg.com\/profile_banners\/126846235\/1370541755","profile_link_color":"0099CC","profile_sidebar_border_color":"FFF8AD","profile_sidebar_fill_color":"F6FFD1","profile_text_color":"333333","profile_use_background_image":true,"default_profile":false,"default_profile_image":false,"following":null,"follow_request_sent":null,"notifications":null},"geo":null,"coordinates":null,"place":null,"contributors":null,"retweet_count":4,"favorite_count":1,"entities":{"hashtags":[],"symbols":[],"urls":[{"url":"http:\/\/t.co\/YIHdEXcNsr","expanded_url":"http:\/\/tl.gd\/n_1rl0ucf","display_url":"tl.gd\/n_1rl0ucf","indices":[113,135]}],"user_mentions":[{"screen_name":"BoAtheKOREA","name":"BoA the KOREA \ubcf4\uc544","id":345776117,"id_str":"345776117","indices":[0,12]}]},"favorited":false,"retweeted":false,"possibly_sensitive":false,"lang":"ko"},"retweet_count":4,"favorite_count":0,"entities":{"hashtags":[],"symbols":[],"urls":[],"user_mentions":[{"screen_name":"yong___2","name":"\uc6a9\uc774\/\u3088\u3093\u3088\u3093","id":126846235,"id_str":"126846235","indices":[3,12]},{"screen_name":"BoAtheKOREA","name":"BoA the KOREA \ubcf4\uc544","id":345776117,"id_str":"345776117","indices":[14,26]}]},"favorited":false,"retweeted":false,"lang":"ko"},{"created_at":"Tue Jun 25 15:34:40 +0000 2013","id":349551223306854401,"id_str":"349551223306854401","text":"RT @yong___2: @BoAtheKOREA \nBoA - Baby you.. \uac00\uc0ac \ubc88\uc5ed(\ub3c5\uc74c+\ub73b) \u3044\u3064\u304b\u3089\u3060\u308d\u3046 \uc774\uce20\uce74\ub77c \ub2e4\ub85c\uc624 \uc5b8\uc81c\ubd80\ud130 \uc600\uc744\uae4c \u4e8c\u4eba\u3060\u3051\u306e love sound \ud6c4\ud0c0\ub9ac\ub2e4\ucf00\ub178 love sound (cont) http:\/\/t.co\/xi\u2026","source":"\u003ca href=\"http:\/\/www.tweetdeck.com\" rel=\"nofollow\"\u003eTweetDeck\u003c\/a\u003e","truncated":false,"in_reply_to_status_id":null,"in_reply_to_status_id_str":null,"in_reply_to_user_id":null,"in_reply_to_user_id_str":null,"in_reply_to_screen_name":null,"user":{"id":345776117,"id_str":"345776117","name":"BoA the KOREA \ubcf4\uc544","screen_name":"BoAtheKOREA","location":"Korea","description":"\ubcf4\uc544\ub354\ucf54\ub9ac\uc544(BoAtheKOREA)  \u25cf \uac00\uc218 \ubcf4\uc544 ( @BoAkwon )\ub2d8\uc5d0 \uad00\ud55c \ubaa8\ub4e0 \uc815\ubcf4\ub97c \ud55c\uad6d\uc5b4\ub85c \uc81c\uacf5\ud569\ub2c8\ub2e4","url":null,"entities":{"description":{"urls":[]}},"protected":false,"followers_count":7422,"friends_count":596,"listed_count":67,"created_at":"Sun Jul 31 04:36:46 +0000 2011","favourites_count":1024,"utc_offset":32400,"time_zone":"Seoul","geo_enabled":false,"verified":false,"statuses_count":7688,"lang":"ko","contributors_enabled":false,"is_translator":false,"profile_background_color":"C0DEED","profile_background_image_url":"http:\/\/a0.twimg.com\/profile_background_images\/645819141\/ycz1u82yqr54i0v1g20a.jpeg","profile_background_image_url_https":"https:\/\/si0.twimg.com\/profile_background_images\/645819141\/ycz1u82yqr54i0v1g20a.jpeg","profile_background_tile":false,"profile_image_url":"http:\/\/a0.twimg.com\/profile_images\/2552492290\/ge3nbql5iz9tm74wizsh_normal.jpeg","profile_image_url_https":"https:\/\/si0.twimg.com\/profile_images\/2552492290\/ge3nbql5iz9tm74wizsh_normal.jpeg","profile_link_color":"0084B4","profile_sidebar_border_color":"C0DEED","profile_sidebar_fill_color":"DDEEF6","profile_text_color":"333333","profile_use_background_image":true,"default_profile":false,"default_profile_image":false,"following":true,"follow_request_sent":null,"notifications":null},"geo":null,"coordinates":null,"place":null,"contributors":null,"retweeted_status":{"created_at":"Tue Jun 25 14:00:01 +0000 2013","id":349527403950915585,"id_str":"349527403950915585","text":"@BoAtheKOREA \nBoA - Baby you.. \uac00\uc0ac \ubc88\uc5ed(\ub3c5\uc74c+\ub73b) \u3044\u3064\u304b\u3089\u3060\u308d\u3046 \uc774\uce20\uce74\ub77c \ub2e4\ub85c\uc624 \uc5b8\uc81c\ubd80\ud130 \uc600\uc744\uae4c \u4e8c\u4eba\u3060\u3051\u306e love sound \ud6c4\ud0c0\ub9ac\ub2e4\ucf00\ub178 love sound (cont) http:\/\/t.co\/xitz5A8wJ7","source":"\u003ca href=\"http:\/\/twitter.com\/download\/iphone\" rel=\"nofollow\"\u003eTwitter for iPhone\u003c\/a\u003e","truncated":false,"in_reply_to_status_id":null,"in_reply_to_status_id_str":null,"in_reply_to_user_id":345776117,"in_reply_to_user_id_str":"345776117","in_reply_to_screen_name":"BoAtheKOREA","user":{"id":126846235,"id_str":"126846235","name":"\uc6a9\uc774\/\u3088\u3093\u3088\u3093","screen_name":"yong___2","location":"TIFF's world \u26653\u2665","description":"Korean. but now in Tokyo. \uc598\ub4e4\uc544 \ub3c4\ucfc4\uc880 \uc62c\ub798...?","url":null,"entities":{"description":{"urls":[]}},"protected":false,"followers_count":1191,"friends_count":277,"listed_count":11,"created_at":"Sat Mar 27 05:00:09 +0000 2010","favourites_count":1639,"utc_offset":32400,"time_zone":"Seoul","geo_enabled":true,"verified":false,"statuses_count":69943,"lang":"ko","contributors_enabled":false,"is_translator":false,"profile_background_color":"FFF04D","profile_background_image_url":"http:\/\/a0.twimg.com\/images\/themes\/theme19\/bg.gif","profile_background_image_url_https":"https:\/\/si0.twimg.com\/images\/themes\/theme19\/bg.gif","profile_background_tile":false,"profile_image_url":"http:\/\/a0.twimg.com\/profile_images\/378800000044396650\/d9121c8f23efbfb81a657855ba375f41_normal.jpeg","profile_image_url_https":"https:\/\/si0.twimg.com\/profile_images\/378800000044396650\/d9121c8f23efbfb81a657855ba375f41_normal.jpeg","profile_banner_url":"https:\/\/pbs.twimg.com\/profile_banners\/126846235\/1370541755","profile_link_color":"0099CC","profile_sidebar_border_color":"FFF8AD","profile_sidebar_fill_color":"F6FFD1","profile_text_color":"333333","profile_use_background_image":true,"default_profile":false,"default_profile_image":false,"following":null,"follow_request_sent":null,"notifications":null},"geo":null,"coordinates":null,"place":null,"contributors":null,"retweet_count":2,"favorite_count":0,"entities":{"hashtags":[],"symbols":[],"urls":[{"url":"http:\/\/t.co\/xitz5A8wJ7","expanded_url":"http:\/\/tl.gd\/n_1rl0v8t","display_url":"tl.gd\/n_1rl0v8t","indices":[111,133]}],"user_mentions":[{"screen_name":"BoAtheKOREA","name":"BoA the KOREA \ubcf4\uc544","id":345776117,"id_str":"345776117","indices":[0,12]}]},"favorited":false,"retweeted":false,"possibly_sensitive":false,"lang":"ko"},"retweet_count":2,"favorite_count":0,"entities":{"hashtags":[],"symbols":[],"urls":[],"user_mentions":[{"screen_name":"yong___2","name":"\uc6a9\uc774\/\u3088\u3093\u3088\u3093","id":126846235,"id_str":"126846235","indices":[3,12]},{"screen_name":"BoAtheKOREA","name":"BoA the KOREA \ubcf4\uc544","id":345776117,"id_str":"345776117","indices":[14,26]}]},"favorited":false,"retweeted":false,"lang":"ko"},{"created_at":"Tue Jun 25 15:32:08 +0000 2013","id":349550584933785603,"id_str":"349550584933785603","text":"\u5e02\u5834\u898f\u5f8b\u4e00\u5b9a\u8981\u914d\u5408\u674e\u514b\u5f37\u554a","source":"web","truncated":false,"in_reply_to_status_id":null,"in_reply_to_status_id_str":null,"in_reply_to_user_id":null,"in_reply_to_user_id_str":null,"in_reply_to_screen_name":null,"user":{"id":18325616,"id_str":"18325616","name":"akid","screen_name":"akid_","location":"on line","description":"Sometimes tweet in English, \u6709\u65f6\u5220\u5bf9\u8bdd\u63a8\u3002Contact me if you need translating service for company: akidtongtong # gmail","url":"http:\/\/t.co\/RiUr0MduM9","entities":{"url":{"urls":[{"url":"http:\/\/t.co\/RiUr0MduM9","expanded_url":"http:\/\/akidtongtong.tumblr.com\/","display_url":"akidtongtong.tumblr.com","indices":[0,22]}]},"description":{"urls":[]}},"protected":false,"followers_count":4415,"friends_count":750,"listed_count":88,"created_at":"Tue Dec 23 03:46:48 +0000 2008","favourites_count":1345,"utc_offset":-32400,"time_zone":"Alaska","geo_enabled":true,"verified":false,"statuses_count":33233,"lang":"en","contributors_enabled":false,"is_translator":false,"profile_background_color":"FAF2F2","profile_background_image_url":"http:\/\/a0.twimg.com\/profile_background_images\/554468681\/p589736591.jpg","profile_background_image_url_https":"https:\/\/si0.twimg.com\/profile_background_images\/554468681\/p589736591.jpg","profile_background_tile":false,"profile_image_url":"http:\/\/a0.twimg.com\/profile_images\/3662709812\/526429d356c3f3931847568511d4232e_normal.png","profile_image_url_https":"https:\/\/si0.twimg.com\/profile_images\/3662709812\/526429d356c3f3931847568511d4232e_normal.png","profile_banner_url":"https:\/\/pbs.twimg.com\/profile_banners\/18325616\/1364576749","profile_link_color":"E061AB","profile_sidebar_border_color":"FFFFFF","profile_sidebar_fill_color":"79E633","profile_text_color":"3C3940","profile_use_background_image":true,"default_profile":false,"default_profile_image":false,"following":true,"follow_request_sent":null,"notifications":null},"geo":null,"coordinates":null,"place":null,"contributors":null,"retweet_count":0,"favorite_count":0,"entities":{"hashtags":[],"symbols":[],"urls":[],"user_mentions":[]},"favorited":false,"retweeted":false,"lang":"zh"},{"created_at":"Tue Jun 25 15:29:29 +0000 2013","id":349549919134167040,"id_str":"349549919134167040","text":"\u5927\u96e8\u7684\u591c #weather #instaweather #instaweatherpro  #sky #outdoors #nature  #instagood #photooftheday\u2026 http:\/\/t.co\/NqyKq69DrW","source":"\u003ca href=\"http:\/\/instagram.com\" rel=\"nofollow\"\u003eInstagram\u003c\/a\u003e","truncated":false,"in_reply_to_status_id":null,"in_reply_to_status_id_str":null,"in_reply_to_user_id":null,"in_reply_to_user_id_str":null,"in_reply_to_screen_name":null,"user":{"id":59032339,"id_str":"59032339","name":"\u964c\u4e0a\u82b1\u5f00\u264d","screen_name":"Ivy905","location":"Shanghai","description":"\u6211\u8981\u7684\u4e0d\u8fc7\u662f\u7231\u4e0e\u8bda","url":null,"entities":{"description":{"urls":[]}},"protected":false,"followers_count":2974,"friends_count":244,"listed_count":127,"created_at":"Wed Jul 22 04:15:56 +0000 2009","favourites_count":181,"utc_offset":28800,"time_zone":"Beijing","geo_enabled":true,"verified":false,"statuses_count":53438,"lang":"en","contributors_enabled":false,"is_translator":false,"profile_background_color":"FFF04D","profile_background_image_url":"http:\/\/a0.twimg.com\/images\/themes\/theme19\/bg.gif","profile_background_image_url_https":"https:\/\/si0.twimg.com\/images\/themes\/theme19\/bg.gif","profile_background_tile":false,"profile_image_url":"http:\/\/a0.twimg.com\/profile_images\/378800000033696762\/59edba16d298c2c6262dba4117063753_normal.jpeg","profile_image_url_https":"https:\/\/si0.twimg.com\/profile_images\/378800000033696762\/59edba16d298c2c6262dba4117063753_normal.jpeg","profile_link_color":"0099CC","profile_sidebar_border_color":"FFF8AD","profile_sidebar_fill_color":"F6FFD1","profile_text_color":"333333","profile_use_background_image":true,"default_profile":false,"default_profile_image":false,"following":true,"follow_request_sent":null,"notifications":null},"geo":null,"coordinates":null,"place":null,"contributors":null,"retweet_count":0,"favorite_count":0,"entities":{"hashtags":[{"text":"weather","indices":[5,13]},{"text":"instaweather","indices":[14,27]},{"text":"instaweatherpro","indices":[28,44]},{"text":"sky","indices":[46,50]},{"text":"outdoors","indices":[51,60]},{"text":"nature","indices":[61,68]},{"text":"instagood","indices":[70,80]},{"text":"photooftheday","indices":[81,95]}],"symbols":[],"urls":[{"url":"http:\/\/t.co\/NqyKq69DrW","expanded_url":"http:\/\/instagram.com\/p\/a_KwJ1vPpS\/","display_url":"instagram.com\/p\/a_KwJ1vPpS\/","indices":[97,119]}],"user_mentions":[]},"favorited":false,"retweeted":false,"possibly_sensitive":false,"lang":"ja"},{"created_at":"Tue Jun 25 15:29:17 +0000 2013","id":349549867191894016,"id_str":"349549867191894016","text":"@PinkyJie reply ok? \u56de\u590d\u6b63\u5e38\u4e0d\uff1f","source":"\u003ca href=\"http:\/\/pinkyjie.com\" rel=\"nofollow\"\u003eTrister \u9524\u65af\u7279\u003c\/a\u003e","truncated":false,"in_reply_to_status_id":349549254198562817,"in_reply_to_status_id_str":"349549254198562817","in_reply_to_user_id":46095305,"in_reply_to_user_id_str":"46095305","in_reply_to_screen_name":"PinkyJie","user":{"id":46095305,"id_str":"46095305","name":"\u9a6c\u65af\u7279","screen_name":"PinkyJie","location":"\u4e0a\u6d77","description":"87\u964d\u751f\u7684\u957f\u76f8\u5a49\u7ea6\u7684\u6328\u8e22\u4ecb\u4eba\u58eb\uff0c\u5e38\u88ab\u5929\u874e\u5ea7\u9119\u89c6\u7684\u5929\u874e\u7537\uff0c\u515c\u513f\u63e3Moto\u7684Android\uff0c\u624b\u62ff\u300a\u6a21\u5f0f\u5206\u7c7b\u300b\uff0c\u7231\u667a\u80fd\u624b\u673a\uff0c\u7231\u8bc6\u522b\uff0c\u72312B\u53f0\u6e7e\u5076\u50cf\u5267\uff0c\u7231\u52a8\u4f5c\u6e38\u620f~\u5730\u4ea7\u5927\u4ea8 @trista099 \u7684\u8ddf\u73ed~\u4ee5\u540e\u53ea\u8bc6\u522b\u5730\u4ea7\u5927\u4ea8\u9524\u5b50~","url":"http:\/\/t.co\/8noiSL6Voi","entities":{"url":{"urls":[{"url":"http:\/\/t.co\/8noiSL6Voi","expanded_url":"http:\/\/pinkyjie.com","display_url":"pinkyjie.com","indices":[0,22]}]},"description":{"urls":[]}},"protected":false,"followers_count":252,"friends_count":218,"listed_count":14,"created_at":"Wed Jun 10 12:02:48 +0000 2009","favourites_count":51,"utc_offset":28800,"time_zone":"Beijing","geo_enabled":true,"verified":false,"statuses_count":13859,"lang":"zh-cn","contributors_enabled":false,"is_translator":false,"profile_background_color":"9AE4E8","profile_background_image_url":"http:\/\/a0.twimg.com\/images\/themes\/theme16\/bg.gif","profile_background_image_url_https":"https:\/\/si0.twimg.com\/images\/themes\/theme16\/bg.gif","profile_background_tile":false,"profile_image_url":"http:\/\/a0.twimg.com\/profile_images\/1180942711\/touxiang_4__normal.jpg","profile_image_url_https":"https:\/\/si0.twimg.com\/profile_images\/1180942711\/touxiang_4__normal.jpg","profile_link_color":"0084B4","profile_sidebar_border_color":"BDDCAD","profile_sidebar_fill_color":"DDFFCC","profile_text_color":"333333","profile_use_background_image":true,"default_profile":false,"default_profile_image":false,"following":true,"follow_request_sent":null,"notifications":null},"geo":null,"coordinates":null,"place":null,"contributors":null,"retweet_count":0,"favorite_count":0,"entities":{"hashtags":[],"symbols":[],"urls":[],"user_mentions":[{"screen_name":"PinkyJie","name":"\u9a6c\u65af\u7279","id":46095305,"id_str":"46095305","indices":[0,9]}]},"favorited":false,"retweeted":false,"lang":"zh"},{"created_at":"Tue Jun 25 15:28:24 +0000 2013","id":349549643878772736,"id_str":"349549643878772736","text":"RT @fufuji97: \u4e94\u56db\u8fd0\u52a8\u9020\u6210\u4e86\u5927\u6279\u65e0\u653f\u5e9c\u4e3b\u4e49\u8005@Xiang_xiaokai \u8fd9\u79cd\u7c7b\u6bd4\u6beb\u65e0\u610f\u4e49\u300220\u5e74\u4ee3\u4e2d\u56fd\u53f7\u79f0\u201c\u5171\u4ea7\u515a\u3001\u9a6c\u514b\u601d\u515a\u7684\u4e0d\u4e0b\u51e0\u5341\u4e2a\uff0c\u540e\u6765\u6210\u529f\u7684\u90a3\u4e2a\uff0c\u662f\u552f\u4e00\u63a5\u53d7\u82cf\u4fc4\u8d44\u52a9\u7684@HeQinglian  \u5386\u53f2\u5c06\u91cd\u590d\uff1a\u4e2d\u5171\u4e00\u5927\u53ec\u5f00\u65f6\u768452\u540d\u515a\u5458\u4e2d\uff0c\u4e0d\u540c\u7a0b\u5ea6\u53d7\u5230\u8fc7\u5404\u79cd\u5f62\u2026","source":"\u003ca href=\"http:\/\/google.com\" rel=\"nofollow\"\u003enewmyteabot27\u003c\/a\u003e","truncated":false,"in_reply_to_status_id":null,"in_reply_to_status_id_str":null,"in_reply_to_user_id":null,"in_reply_to_user_id_str":null,"in_reply_to_screen_name":null,"user":{"id":267502889,"id_str":"267502889","name":"\u4e2d\u6587\u70ed\u63a8\u673a\u5668\u4eba","screen_name":"iruitui","location":"\u8be5\u5730\u5740\u65e0\u6cd5\u663e\u793a","description":"\u5bfb\u627e\u5e76\u8f6c\u53d1\u70ed\u95e8\u6216\u6709\u8da3\u7684\u63a8\u6587\u3002\r\n\r\n\u6240\u8f6c\u53d1\u63a8\u6587\u5e76\u4e0d\u8868\u660e\u672c\u5e10\u53f7\u7ef4\u62a4\u8005\u89c2\u70b9\u3002\u63a8\u6587\u7684\u771f\u4f2a\u4e0e\u5bf9\u9519\u8bf7\u81ea\u884c\u5224\u65ad\u3002\r\n\r\n\u5982\u6709\u88ab\u672c\u63a8\u8f6c\u53d1\u7684\u63a8\u6587\u9700\u8981\u5220\u9664\uff0c\u8bf7\u77e5\u6089 @iruitui\u3002","url":"https:\/\/t.co\/OTUFpm2Idf","entities":{"url":{"urls":[{"url":"https:\/\/t.co\/OTUFpm2Idf","expanded_url":"https:\/\/www.google.com\/ncr","display_url":"google.com\/ncr","indices":[0,23]}]},"description":{"urls":[]}},"protected":false,"followers_count":3367,"friends_count":1,"listed_count":111,"created_at":"Thu Mar 17 01:57:12 +0000 2011","favourites_count":30,"utc_offset":-32400,"time_zone":"Alaska","geo_enabled":false,"verified":false,"statuses_count":98811,"lang":"zh-cn","contributors_enabled":false,"is_translator":false,"profile_background_color":"C0DEED","profile_background_image_url":"http:\/\/a0.twimg.com\/images\/themes\/theme1\/bg.png","profile_background_image_url_https":"https:\/\/si0.twimg.com\/images\/themes\/theme1\/bg.png","profile_background_tile":false,"profile_image_url":"http:\/\/a0.twimg.com\/profile_images\/2830387364\/ab16e3458fd9dec64a098b1e8c1a26f6_normal.png","profile_image_url_https":"https:\/\/si0.twimg.com\/profile_images\/2830387364\/ab16e3458fd9dec64a098b1e8c1a26f6_normal.png","profile_link_color":"0084B4","profile_sidebar_border_color":"C0DEED","profile_sidebar_fill_color":"DDEEF6","profile_text_color":"333333","profile_use_background_image":true,"default_profile":true,"default_profile_image":false,"following":true,"follow_request_sent":null,"notifications":null},"geo":null,"coordinates":null,"place":null,"contributors":null,"retweeted_status":{"created_at":"Tue Jun 25 02:32:19 +0000 2013","id":349354339468451840,"id_str":"349354339468451840","text":"\u4e94\u56db\u8fd0\u52a8\u9020\u6210\u4e86\u5927\u6279\u65e0\u653f\u5e9c\u4e3b\u4e49\u8005@Xiang_xiaokai \u8fd9\u79cd\u7c7b\u6bd4\u6beb\u65e0\u610f\u4e49\u300220\u5e74\u4ee3\u4e2d\u56fd\u53f7\u79f0\u201c\u5171\u4ea7\u515a\u3001\u9a6c\u514b\u601d\u515a\u7684\u4e0d\u4e0b\u51e0\u5341\u4e2a\uff0c\u540e\u6765\u6210\u529f\u7684\u90a3\u4e2a\uff0c\u662f\u552f\u4e00\u63a5\u53d7\u82cf\u4fc4\u8d44\u52a9\u7684@HeQinglian  \u5386\u53f2\u5c06\u91cd\u590d\uff1a\u4e2d\u5171\u4e00\u5927\u53ec\u5f00\u65f6\u768452\u540d\u515a\u5458\u4e2d\uff0c\u4e0d\u540c\u7a0b\u5ea6\u53d7\u5230\u8fc7\u5404\u79cd\u5f62\u5f0f\u65e0\u653f\u5e9c\u4e3b\u4e49\u601d\u6f6e\u5f71\u54cd\u7684\u5c31\u670922","source":"web","truncated":false,"in_reply_to_status_id":349352762338836481,"in_reply_to_status_id_str":"349352762338836481","in_reply_to_user_id":381592615,"in_reply_to_user_id_str":"381592615","in_reply_to_screen_name":"Xiang_xiaokai","user":{"id":53372202,"id_str":"53372202","name":"fufuji97","screen_name":"fufuji97","location":"\u4e2d\u534e\u516c\u6c11\u5408\u4f17\u56fd","description":"\u8709\u8763\u4e00\u53ea\r\n\r\n\u4e94\u6bdb\u5982FO\u6211\uff0c\u5f53\u5fc3\u906d\u96f7\u51fb\uff0c\u7537\u7684\u9633\u4e0d\u4e3e\uff0c\u5973\u7684\u5b55\u7387\u4f4e\uff0c\u751f\u5b50\u65e0\u83ca\u83ca\uff0c\u751f\u5973\u77f3BB\uff0c\u6025\u6025\u5982\u5f8b\u4ee4\uff0c\u98ce\u706b\u96f7\u7535\u9739\uff01","url":null,"entities":{"description":{"urls":[]}},"protected":false,"followers_count":4137,"friends_count":116,"listed_count":36,"created_at":"Fri Jul 03 12:32:11 +0000 2009","favourites_count":108,"utc_offset":28800,"time_zone":"Beijing","geo_enabled":false,"verified":false,"statuses_count":38079,"lang":"en","contributors_enabled":false,"is_translator":false,"profile_background_color":"B5E61D","profile_background_image_url":"http:\/\/a0.twimg.com\/profile_background_images\/713590328\/abc3f780028c2938ccf6bc900f93a829.jpeg","profile_background_image_url_https":"https:\/\/si0.twimg.com\/profile_background_images\/713590328\/abc3f780028c2938ccf6bc900f93a829.jpeg","profile_background_tile":false,"profile_image_url":"http:\/\/a0.twimg.com\/profile_images\/3681701429\/2b4a24206e43a922c3dc9b8dfa0c297a_normal.png","profile_image_url_https":"https:\/\/si0.twimg.com\/profile_images\/3681701429\/2b4a24206e43a922c3dc9b8dfa0c297a_normal.png","profile_banner_url":"https:\/\/pbs.twimg.com\/profile_banners\/53372202\/1353119211","profile_link_color":"A349A4","profile_sidebar_border_color":"FFFFFF","profile_sidebar_fill_color":"FFF7CC","profile_text_color":"0C3E53","profile_use_background_image":true,"default_profile":false,"default_profile_image":false,"following":null,"follow_request_sent":null,"notifications":null},"geo":null,"coordinates":null,"place":null,"contributors":null,"retweet_count":1,"favorite_count":0,"entities":{"hashtags":[],"symbols":[],"urls":[],"user_mentions":[{"screen_name":"Xiang_xiaokai","name":"\u9879\u5c0f\u51ef","id":381592615,"id_str":"381592615","indices":[15,29]},{"screen_name":"HeQinglian","name":"He Qinglian","id":126798663,"id_str":"126798663","indices":[81,92]}]},"favorited":false,"retweeted":false,"lang":"zh"},"retweet_count":1,"favorite_count":0,"entities":{"hashtags":[],"symbols":[],"urls":[],"user_mentions":[{"screen_name":"fufuji97","name":"fufuji97","id":53372202,"id_str":"53372202","indices":[3,12]},{"screen_name":"Xiang_xiaokai","name":"\u9879\u5c0f\u51ef","id":381592615,"id_str":"381592615","indices":[29,43]},{"screen_name":"HeQinglian","name":"He Qinglian","id":126798663,"id_str":"126798663","indices":[95,106]}]},"favorited":false,"retweeted":false,"lang":"zh"},{"created_at":"Tue Jun 25 15:27:32 +0000 2013","id":349549426425073667,"id_str":"349549426425073667","text":"\u7537\u7684\u8fd8\u662f\u5973\u7684\uff1f RT @seiyagg: \u00a0\u70e7\u6b7b RT @Deirdre____: \u00a0\u6652RT @zzzqaz: \u7f05\u6000\u4e00\u4e0b\u6211\u7684\u521d\u543b\u3002\u3002\u3002 https:\/\/t.co\/aDvSbEbjrm","source":"\u003ca href=\"http:\/\/td8.me\" rel=\"nofollow\"\u003e\u63a8\u5012\u5427\uff01\u5c11\u5e74\uff01\u003c\/a\u003e","truncated":false,"in_reply_to_status_id":null,"in_reply_to_status_id_str":null,"in_reply_to_user_id":null,"in_reply_to_user_id_str":null,"in_reply_to_screen_name":null,"user":{"id":303090240,"id_str":"303090240","name":"\u5446\u5446\u59b9","screen_name":"aibubu7","location":"Shanghai","description":"\u627e\u4e00\u4e2a\u4eba\u60fa\u60fa\u76f8\u60dc\uff0c\u627e\u4e00\u9897\u5fc3\u5fc3\u5fc3\u76f8\u5370","url":null,"entities":{"description":{"urls":[]}},"protected":false,"followers_count":1236,"friends_count":230,"listed_count":34,"created_at":"Sun May 22 08:46:20 +0000 2011","favourites_count":304,"utc_offset":28800,"time_zone":"Hong Kong","geo_enabled":true,"verified":false,"statuses_count":39577,"lang":"en","contributors_enabled":false,"is_translator":false,"profile_background_color":"9AE4E8","profile_background_image_url":"http:\/\/a0.twimg.com\/images\/themes\/theme16\/bg.gif","profile_background_image_url_https":"https:\/\/si0.twimg.com\/images\/themes\/theme16\/bg.gif","profile_background_tile":false,"profile_image_url":"http:\/\/a0.twimg.com\/profile_images\/2503927562\/ua58jyjqddlwhrkyagw0_normal.jpeg","profile_image_url_https":"https:\/\/si0.twimg.com\/profile_images\/2503927562\/ua58jyjqddlwhrkyagw0_normal.jpeg","profile_link_color":"0084B4","profile_sidebar_border_color":"BDDCAD","profile_sidebar_fill_color":"DDFFCC","profile_text_color":"333333","profile_use_background_image":true,"default_profile":false,"default_profile_image":false,"following":true,"follow_request_sent":null,"notifications":null},"geo":null,"coordinates":null,"place":null,"contributors":null,"retweet_count":0,"favorite_count":0,"entities":{"hashtags":[],"symbols":[],"urls":[{"url":"https:\/\/t.co\/aDvSbEbjrm","expanded_url":"https:\/\/pbs.twimg.com\/media\/BNnYOsjCcAAVOHJ.jpg","display_url":"pbs.twimg.com\/media\/BNnYOsjC\u2026","indices":[68,91]}],"user_mentions":[{"screen_name":"seiyagg","name":"\u76ae\u76ae\u5927\u738b","id":137240910,"id_str":"137240910","indices":[11,19]},{"screen_name":"Deirdre____","name":"\u5fb7\u5fb7","id":136249402,"id_str":"136249402","indices":[28,40]},{"screen_name":"zzzqaz","name":"\u5c0f\u7334\u7eb8","id":80065366,"id_str":"80065366","indices":[47,54]}]},"favorited":false,"retweeted":false,"possibly_sensitive":false,"lang":"zh"},{"created_at":"Tue Jun 25 15:27:25 +0000 2013","id":349549397157228544,"id_str":"349549397157228544","text":"\u7ec6\u8282\u63a7\u3002\u3002\u3002\u7ea0\u7ed3\u4e8e\u7ec6\u8282\u771f\u7684\u4e0d\u662f\u4ef6\u597d\u4e8b","source":"\u003ca href=\"http:\/\/tapbots.com\/tweetbot\" rel=\"nofollow\"\u003eTweetbot for iOS\u003c\/a\u003e","truncated":false,"in_reply_to_status_id":null,"in_reply_to_status_id_str":null,"in_reply_to_user_id":null,"in_reply_to_user_id_str":null,"in_reply_to_screen_name":null,"user":{"id":59032339,"id_str":"59032339","name":"\u964c\u4e0a\u82b1\u5f00\u264d","screen_name":"Ivy905","location":"Shanghai","description":"\u6211\u8981\u7684\u4e0d\u8fc7\u662f\u7231\u4e0e\u8bda","url":null,"entities":{"description":{"urls":[]}},"protected":false,"followers_count":2974,"friends_count":244,"listed_count":127,"created_at":"Wed Jul 22 04:15:56 +0000 2009","favourites_count":181,"utc_offset":28800,"time_zone":"Beijing","geo_enabled":true,"verified":false,"statuses_count":53438,"lang":"en","contributors_enabled":false,"is_translator":false,"profile_background_color":"FFF04D","profile_background_image_url":"http:\/\/a0.twimg.com\/images\/themes\/theme19\/bg.gif","profile_background_image_url_https":"https:\/\/si0.twimg.com\/images\/themes\/theme19\/bg.gif","profile_background_tile":false,"profile_image_url":"http:\/\/a0.twimg.com\/profile_images\/378800000033696762\/59edba16d298c2c6262dba4117063753_normal.jpeg","profile_image_url_https":"https:\/\/si0.twimg.com\/profile_images\/378800000033696762\/59edba16d298c2c6262dba4117063753_normal.jpeg","profile_link_color":"0099CC","profile_sidebar_border_color":"FFF8AD","profile_sidebar_fill_color":"F6FFD1","profile_text_color":"333333","profile_use_background_image":true,"default_profile":false,"default_profile_image":false,"following":true,"follow_request_sent":null,"notifications":null},"geo":null,"coordinates":null,"place":null,"contributors":null,"retweet_count":0,"favorite_count":0,"entities":{"hashtags":[],"symbols":[],"urls":[],"user_mentions":[]},"favorited":false,"retweeted":false,"lang":"zh"},{"created_at":"Tue Jun 25 15:27:05 +0000 2013","id":349549313409556480,"id_str":"349549313409556480","text":"Meet our fish, Tupac and Biggie Smalls, who live together in harmony as our #London office pets:\u00a0 http:\/\/t.co\/yVuxiQUXZD","source":"\u003ca href=\"http:\/\/www.exacttarget.com\/social\" rel=\"nofollow\"\u003eSocialEngage\u003c\/a\u003e","truncated":false,"in_reply_to_status_id":null,"in_reply_to_status_id_str":null,"in_reply_to_user_id":null,"in_reply_to_user_id_str":null,"in_reply_to_screen_name":null,"user":{"id":2142731,"id_str":"2142731","name":"Firefox","screen_name":"firefox","location":"All over the world","description":"I make the web a little faster, safer, smarter, better.","url":"http:\/\/t.co\/yE4rUZYydZ","entities":{"url":{"urls":[{"url":"http:\/\/t.co\/yE4rUZYydZ","expanded_url":"http:\/\/blog.mozilla.org\/","display_url":"blog.mozilla.org","indices":[0,22]}]},"description":{"urls":[]}},"protected":false,"followers_count":1632769,"friends_count":326292,"listed_count":23913,"created_at":"Sat Mar 24 23:58:14 +0000 2007","favourites_count":1672,"utc_offset":-28800,"time_zone":"Pacific Time (US & Canada)","geo_enabled":false,"verified":true,"statuses_count":7170,"lang":"en","contributors_enabled":false,"is_translator":false,"profile_background_color":"00539F","profile_background_image_url":"http:\/\/a0.twimg.com\/profile_background_images\/803517359\/a9781eb119565e03dc6f15be6e77c5ba.jpeg","profile_background_image_url_https":"https:\/\/si0.twimg.com\/profile_background_images\/803517359\/a9781eb119565e03dc6f15be6e77c5ba.jpeg","profile_background_tile":false,"profile_image_url":"http:\/\/a0.twimg.com\/profile_images\/3302774296\/606a53ef3edfe9633c6f08a4076a5664_normal.png","profile_image_url_https":"https:\/\/si0.twimg.com\/profile_images\/3302774296\/606a53ef3edfe9633c6f08a4076a5664_normal.png","profile_banner_url":"https:\/\/pbs.twimg.com\/profile_banners\/2142731\/1366395406","profile_link_color":"CC3300","profile_sidebar_border_color":"FFFFFF","profile_sidebar_fill_color":"FFFF99","profile_text_color":"333333","profile_use_background_image":true,"default_profile":false,"default_profile_image":false,"following":true,"follow_request_sent":null,"notifications":null},"geo":null,"coordinates":null,"place":null,"contributors":null,"retweet_count":17,"favorite_count":22,"entities":{"hashtags":[{"text":"London","indices":[76,83]}],"symbols":[],"urls":[{"url":"http:\/\/t.co\/yVuxiQUXZD","expanded_url":"http:\/\/twitpic.com\/cz4tds","display_url":"twitpic.com\/cz4tds","indices":[98,120]}],"user_mentions":[]},"favorited":false,"retweeted":false,"possibly_sensitive":false,"lang":"en"},{"created_at":"Tue Jun 25 15:26:51 +0000 2013","id":349549254198562817,"id_str":"349549254198562817","text":"\u6d4b\u8bd5\u4e00\u4e0b~ RT @huajie1984:RT @motodexter: \u4e2d\u82f1\u6587\u5bf9\u7167\u7ffb\u8bd1\uff1a\"It's gonna be ok.\"=\u300e\u8981\u76f8\u4fe1\u515a\u548c\u653f\u5e9c\u3002\u300f","source":"\u003ca href=\"http:\/\/pinkyjie.com\" rel=\"nofollow\"\u003eTrister \u9524\u65af\u7279\u003c\/a\u003e","truncated":false,"in_reply_to_status_id":null,"in_reply_to_status_id_str":null,"in_reply_to_user_id":null,"in_reply_to_user_id_str":null,"in_reply_to_screen_name":null,"user":{"id":46095305,"id_str":"46095305","name":"\u9a6c\u65af\u7279","screen_name":"PinkyJie","location":"\u4e0a\u6d77","description":"87\u964d\u751f\u7684\u957f\u76f8\u5a49\u7ea6\u7684\u6328\u8e22\u4ecb\u4eba\u58eb\uff0c\u5e38\u88ab\u5929\u874e\u5ea7\u9119\u89c6\u7684\u5929\u874e\u7537\uff0c\u515c\u513f\u63e3Moto\u7684Android\uff0c\u624b\u62ff\u300a\u6a21\u5f0f\u5206\u7c7b\u300b\uff0c\u7231\u667a\u80fd\u624b\u673a\uff0c\u7231\u8bc6\u522b\uff0c\u72312B\u53f0\u6e7e\u5076\u50cf\u5267\uff0c\u7231\u52a8\u4f5c\u6e38\u620f~\u5730\u4ea7\u5927\u4ea8 @trista099 \u7684\u8ddf\u73ed~\u4ee5\u540e\u53ea\u8bc6\u522b\u5730\u4ea7\u5927\u4ea8\u9524\u5b50~","url":"http:\/\/t.co\/8noiSL6Voi","entities":{"url":{"urls":[{"url":"http:\/\/t.co\/8noiSL6Voi","expanded_url":"http:\/\/pinkyjie.com","display_url":"pinkyjie.com","indices":[0,22]}]},"description":{"urls":[]}},"protected":false,"followers_count":252,"friends_count":218,"listed_count":14,"created_at":"Wed Jun 10 12:02:48 +0000 2009","favourites_count":51,"utc_offset":28800,"time_zone":"Beijing","geo_enabled":true,"verified":false,"statuses_count":13859,"lang":"zh-cn","contributors_enabled":false,"is_translator":false,"profile_background_color":"9AE4E8","profile_background_image_url":"http:\/\/a0.twimg.com\/images\/themes\/theme16\/bg.gif","profile_background_image_url_https":"https:\/\/si0.twimg.com\/images\/themes\/theme16\/bg.gif","profile_background_tile":false,"profile_image_url":"http:\/\/a0.twimg.com\/profile_images\/1180942711\/touxiang_4__normal.jpg","profile_image_url_https":"https:\/\/si0.twimg.com\/profile_images\/1180942711\/touxiang_4__normal.jpg","profile_link_color":"0084B4","profile_sidebar_border_color":"BDDCAD","profile_sidebar_fill_color":"DDFFCC","profile_text_color":"333333","profile_use_background_image":true,"default_profile":false,"default_profile_image":false,"following":true,"follow_request_sent":null,"notifications":null},"geo":null,"coordinates":null,"place":null,"contributors":null,"retweet_count":0,"favorite_count":0,"entities":{"hashtags":[],"symbols":[],"urls":[],"user_mentions":[{"screen_name":"huajie1984","name":"West.Williams \uf8ff","id":65776376,"id_str":"65776376","indices":[9,20]},{"screen_name":"motodexter","name":"Patrick","id":92207864,"id_str":"92207864","indices":[24,35]}]},"favorited":false,"retweeted":false,"lang":"zh"},{"created_at":"Tue Jun 25 15:26:14 +0000 2013","id":349549100531843074,"id_str":"349549100531843074","text":"\u968f\u624b\u7ffb\u4e86\u4e0b\u90a3\u4e9bfo\u6211\u7684\u4eba\uff0cB\u6389\u51e0\u4e2a\u86cb\u5934\u548c\u4e94\u6bdb","source":"\u003ca href=\"http:\/\/tapbots.com\/tweetbot\" rel=\"nofollow\"\u003eTweetbot for iOS\u003c\/a\u003e","truncated":false,"in_reply_to_status_id":null,"in_reply_to_status_id_str":null,"in_reply_to_user_id":null,"in_reply_to_user_id_str":null,"in_reply_to_screen_name":null,"user":{"id":59032339,"id_str":"59032339","name":"\u964c\u4e0a\u82b1\u5f00\u264d","screen_name":"Ivy905","location":"Shanghai","description":"\u6211\u8981\u7684\u4e0d\u8fc7\u662f\u7231\u4e0e\u8bda","url":null,"entities":{"description":{"urls":[]}},"protected":false,"followers_count":2974,"friends_count":244,"listed_count":127,"created_at":"Wed Jul 22 04:15:56 +0000 2009","favourites_count":181,"utc_offset":28800,"time_zone":"Beijing","geo_enabled":true,"verified":false,"statuses_count":53438,"lang":"en","contributors_enabled":false,"is_translator":false,"profile_background_color":"FFF04D","profile_background_image_url":"http:\/\/a0.twimg.com\/images\/themes\/theme19\/bg.gif","profile_background_image_url_https":"https:\/\/si0.twimg.com\/images\/themes\/theme19\/bg.gif","profile_background_tile":false,"profile_image_url":"http:\/\/a0.twimg.com\/profile_images\/378800000033696762\/59edba16d298c2c6262dba4117063753_normal.jpeg","profile_image_url_https":"https:\/\/si0.twimg.com\/profile_images\/378800000033696762\/59edba16d298c2c6262dba4117063753_normal.jpeg","profile_link_color":"0099CC","profile_sidebar_border_color":"FFF8AD","profile_sidebar_fill_color":"F6FFD1","profile_text_color":"333333","profile_use_background_image":true,"default_profile":false,"default_profile_image":false,"following":true,"follow_request_sent":null,"notifications":null},"geo":null,"coordinates":null,"place":null,"contributors":null,"retweet_count":0,"favorite_count":0,"entities":{"hashtags":[],"symbols":[],"urls":[],"user_mentions":[]},"favorited":false,"retweeted":false,"lang":"zh"},{"created_at":"Tue Jun 25 15:26:10 +0000 2013","id":349549083117101056,"id_str":"349549083117101056","text":"[\uc815\ubcf4] \uc624\ub298 BoA\u300cTail of Hope\u300d\ubc1c\ub9e4\uae30\ub150DAY\ub85c 26,28,30\uc77c \ud0c0\uc6cc\ub808\ucf54\ub4dc \uc2dc\ubd80\uc57c\uc810\uc5d0\uc11c \u300cTail\u2019s Photo\u300d\uc774\ubca4\ud2b8 \uc2e4\uc2dc! http:\/\/t.co\/D0ClHC6QXM \ubcf4\uc544\ubd80\ucc44\ub3c4 \ubc30\ud3ec\ud55c\ub370\uc694!^^ http:\/\/t.co\/aHONJ8zXea","source":"\u003ca href=\"http:\/\/www.tweetdeck.com\" rel=\"nofollow\"\u003eTweetDeck\u003c\/a\u003e","truncated":false,"in_reply_to_status_id":null,"in_reply_to_status_id_str":null,"in_reply_to_user_id":null,"in_reply_to_user_id_str":null,"in_reply_to_screen_name":null,"user":{"id":345776117,"id_str":"345776117","name":"BoA the KOREA \ubcf4\uc544","screen_name":"BoAtheKOREA","location":"Korea","description":"\ubcf4\uc544\ub354\ucf54\ub9ac\uc544(BoAtheKOREA)  \u25cf \uac00\uc218 \ubcf4\uc544 ( @BoAkwon )\ub2d8\uc5d0 \uad00\ud55c \ubaa8\ub4e0 \uc815\ubcf4\ub97c \ud55c\uad6d\uc5b4\ub85c \uc81c\uacf5\ud569\ub2c8\ub2e4","url":null,"entities":{"description":{"urls":[]}},"protected":false,"followers_count":7422,"friends_count":596,"listed_count":67,"created_at":"Sun Jul 31 04:36:46 +0000 2011","favourites_count":1024,"utc_offset":32400,"time_zone":"Seoul","geo_enabled":false,"verified":false,"statuses_count":7688,"lang":"ko","contributors_enabled":false,"is_translator":false,"profile_background_color":"C0DEED","profile_background_image_url":"http:\/\/a0.twimg.com\/profile_background_images\/645819141\/ycz1u82yqr54i0v1g20a.jpeg","profile_background_image_url_https":"https:\/\/si0.twimg.com\/profile_background_images\/645819141\/ycz1u82yqr54i0v1g20a.jpeg","profile_background_tile":false,"profile_image_url":"http:\/\/a0.twimg.com\/profile_images\/2552492290\/ge3nbql5iz9tm74wizsh_normal.jpeg","profile_image_url_https":"https:\/\/si0.twimg.com\/profile_images\/2552492290\/ge3nbql5iz9tm74wizsh_normal.jpeg","profile_link_color":"0084B4","profile_sidebar_border_color":"C0DEED","profile_sidebar_fill_color":"DDEEF6","profile_text_color":"333333","profile_use_background_image":true,"default_profile":false,"default_profile_image":false,"following":true,"follow_request_sent":null,"notifications":null},"geo":null,"coordinates":null,"place":null,"contributors":null,"retweet_count":4,"favorite_count":0,"entities":{"hashtags":[],"symbols":[],"urls":[{"url":"http:\/\/t.co\/D0ClHC6QXM","expanded_url":"http:\/\/avex.jp\/boa\/news\/news_detail.php?id=1002899","display_url":"avex.jp\/boa\/news\/news_\u2026","indices":[79,101]}],"user_mentions":[],"media":[{"id":349545933828145152,"id_str":"349545933828145152","indices":[117,139],"media_url":"http:\/\/pbs.twimg.com\/media\/BNnWLMKCQAAso3S.jpg","media_url_https":"https:\/\/pbs.twimg.com\/media\/BNnWLMKCQAAso3S.jpg","url":"http:\/\/t.co\/aHONJ8zXea","display_url":"pic.twitter.com\/aHONJ8zXea","expanded_url":"http:\/\/twitter.com\/BoA_avex_staff\/status\/349545933819756545\/photo\/1","type":"photo","sizes":{"medium":{"w":600,"h":600,"resize":"fit"},"large":{"w":640,"h":640,"resize":"fit"},"thumb":{"w":150,"h":150,"resize":"crop"},"small":{"w":340,"h":340,"resize":"fit"}},"source_status_id":349545933819756545,"source_status_id_str":"349545933819756545"}]},"favorited":false,"retweeted":false,"possibly_sensitive":false,"lang":"ko"},{"created_at":"Tue Jun 25 15:25:26 +0000 2013","id":349548900731981826,"id_str":"349548900731981826","text":"(\u00ac_\u00ac) \u201c@stellaqian: \u4e5f\u8bb8\u53ea\u662f\u56e0\u4e3a\u6211\u80f8\u5927\uff0c\u6709\u65f6\u8eba\u5582\u538b\u4f4f\u4e86\u800c\u5df2\uff1f#\u5582\u5976\u662f\u4e2a\u6280\u672f\u6d3b\u201d","source":"\u003ca href=\"http:\/\/tapbots.com\/tweetbot\" rel=\"nofollow\"\u003eTweetbot for iOS\u003c\/a\u003e","truncated":false,"in_reply_to_status_id":null,"in_reply_to_status_id_str":null,"in_reply_to_user_id":null,"in_reply_to_user_id_str":null,"in_reply_to_screen_name":null,"user":{"id":59032339,"id_str":"59032339","name":"\u964c\u4e0a\u82b1\u5f00\u264d","screen_name":"Ivy905","location":"Shanghai","description":"\u6211\u8981\u7684\u4e0d\u8fc7\u662f\u7231\u4e0e\u8bda","url":null,"entities":{"description":{"urls":[]}},"protected":false,"followers_count":2974,"friends_count":244,"listed_count":127,"created_at":"Wed Jul 22 04:15:56 +0000 2009","favourites_count":181,"utc_offset":28800,"time_zone":"Beijing","geo_enabled":true,"verified":false,"statuses_count":53438,"lang":"en","contributors_enabled":false,"is_translator":false,"profile_background_color":"FFF04D","profile_background_image_url":"http:\/\/a0.twimg.com\/images\/themes\/theme19\/bg.gif","profile_background_image_url_https":"https:\/\/si0.twimg.com\/images\/themes\/theme19\/bg.gif","profile_background_tile":false,"profile_image_url":"http:\/\/a0.twimg.com\/profile_images\/378800000033696762\/59edba16d298c2c6262dba4117063753_normal.jpeg","profile_image_url_https":"https:\/\/si0.twimg.com\/profile_images\/378800000033696762\/59edba16d298c2c6262dba4117063753_normal.jpeg","profile_link_color":"0099CC","profile_sidebar_border_color":"FFF8AD","profile_sidebar_fill_color":"F6FFD1","profile_text_color":"333333","profile_use_background_image":true,"default_profile":false,"default_profile_image":false,"following":true,"follow_request_sent":null,"notifications":null},"geo":null,"coordinates":null,"place":null,"contributors":null,"retweet_count":0,"favorite_count":0,"entities":{"hashtags":[{"text":"\u5582\u5976\u662f\u4e2a\u6280\u672f\u6d3b","indices":[40,48]}],"symbols":[],"urls":[],"user_mentions":[{"screen_name":"stellaqian","name":"\u53f2\u9edb\u62c9 ","id":23012220,"id_str":"23012220","indices":[7,18]}]},"favorited":false,"retweeted":false,"lang":"zh"},{"created_at":"Tue Jun 25 15:21:09 +0000 2013","id":349547822250598401,"id_str":"349547822250598401","text":"RT @huajie1984:RT @motodexter: \u4e2d\u82f1\u6587\u5bf9\u7167\u7ffb\u8bd1\uff1a\"It's gonna be ok.\"=\u300e\u8981\u76f8\u4fe1\u515a\u548c\u653f\u5e9c\u3002\u300f","source":"\u003ca href=\"http:\/\/google.com\" rel=\"nofollow\"\u003enewmyteabot27\u003c\/a\u003e","truncated":false,"in_reply_to_status_id":null,"in_reply_to_status_id_str":null,"in_reply_to_user_id":null,"in_reply_to_user_id_str":null,"in_reply_to_screen_name":null,"user":{"id":267502889,"id_str":"267502889","name":"\u4e2d\u6587\u70ed\u63a8\u673a\u5668\u4eba","screen_name":"iruitui","location":"\u8be5\u5730\u5740\u65e0\u6cd5\u663e\u793a","description":"\u5bfb\u627e\u5e76\u8f6c\u53d1\u70ed\u95e8\u6216\u6709\u8da3\u7684\u63a8\u6587\u3002\r\n\r\n\u6240\u8f6c\u53d1\u63a8\u6587\u5e76\u4e0d\u8868\u660e\u672c\u5e10\u53f7\u7ef4\u62a4\u8005\u89c2\u70b9\u3002\u63a8\u6587\u7684\u771f\u4f2a\u4e0e\u5bf9\u9519\u8bf7\u81ea\u884c\u5224\u65ad\u3002\r\n\r\n\u5982\u6709\u88ab\u672c\u63a8\u8f6c\u53d1\u7684\u63a8\u6587\u9700\u8981\u5220\u9664\uff0c\u8bf7\u77e5\u6089 @iruitui\u3002","url":"https:\/\/t.co\/OTUFpm2Idf","entities":{"url":{"urls":[{"url":"https:\/\/t.co\/OTUFpm2Idf","expanded_url":"https:\/\/www.google.com\/ncr","display_url":"google.com\/ncr","indices":[0,23]}]},"description":{"urls":[]}},"protected":false,"followers_count":3367,"friends_count":1,"listed_count":111,"created_at":"Thu Mar 17 01:57:12 +0000 2011","favourites_count":30,"utc_offset":-32400,"time_zone":"Alaska","geo_enabled":false,"verified":false,"statuses_count":98811,"lang":"zh-cn","contributors_enabled":false,"is_translator":false,"profile_background_color":"C0DEED","profile_background_image_url":"http:\/\/a0.twimg.com\/images\/themes\/theme1\/bg.png","profile_background_image_url_https":"https:\/\/si0.twimg.com\/images\/themes\/theme1\/bg.png","profile_background_tile":false,"profile_image_url":"http:\/\/a0.twimg.com\/profile_images\/2830387364\/ab16e3458fd9dec64a098b1e8c1a26f6_normal.png","profile_image_url_https":"https:\/\/si0.twimg.com\/profile_images\/2830387364\/ab16e3458fd9dec64a098b1e8c1a26f6_normal.png","profile_link_color":"0084B4","profile_sidebar_border_color":"C0DEED","profile_sidebar_fill_color":"DDEEF6","profile_text_color":"333333","profile_use_background_image":true,"default_profile":true,"default_profile_image":false,"following":true,"follow_request_sent":null,"notifications":null},"geo":null,"coordinates":null,"place":null,"contributors":null,"retweet_count":1,"favorite_count":1,"entities":{"hashtags":[],"symbols":[],"urls":[],"user_mentions":[{"screen_name":"huajie1984","name":"West.Williams \uf8ff","id":65776376,"id_str":"65776376","indices":[3,14]},{"screen_name":"motodexter","name":"Patrick","id":92207864,"id_str":"92207864","indices":[18,29]}]},"favorited":false,"retweeted":false,"lang":"zh"},{"created_at":"Tue Jun 25 15:19:23 +0000 2013","id":349547377692127233,"id_str":"349547377692127233","text":"Wireless Keyboard\u7535\u6c60\u6ca1\u7535\u4e86\u3002\u3002\u3002\u4e8e\u662f\u53ea\u80fd\u638f\u51fa\u5c18\u5c01\u5df2\u4e45\u7684HHKB\u5c06\u5c31\u4e00\u4e0b\u4e86\u3002\u3002\u3002 #HHKBSucks","source":"\u003ca href=\"http:\/\/tapbots.com\/software\/tweetbot\/mac\" rel=\"nofollow\"\u003eTweetbot for Mac\u003c\/a\u003e","truncated":false,"in_reply_to_status_id":null,"in_reply_to_status_id_str":null,"in_reply_to_user_id":null,"in_reply_to_user_id_str":null,"in_reply_to_screen_name":null,"user":{"id":75465858,"id_str":"75465858","name":"zzzcn","screen_name":"zzzcn","location":"Hong Kong","description":"#HSFZ #SYSU #HKU | Linux Idiot | Hopeless Apple Fan | Pseudo Programmer | GTD\/ZTD","url":"http:\/\/t.co\/aD6Ali9glj","entities":{"url":{"urls":[{"url":"http:\/\/t.co\/aD6Ali9glj","expanded_url":"http:\/\/zzzcn.info","display_url":"zzzcn.info","indices":[0,22]}]},"description":{"urls":[]}},"protected":false,"followers_count":1252,"friends_count":323,"listed_count":65,"created_at":"Sat Sep 19 03:52:53 +0000 2009","favourites_count":812,"utc_offset":28800,"time_zone":"Hong Kong","geo_enabled":true,"verified":false,"statuses_count":4543,"lang":"en","contributors_enabled":false,"is_translator":false,"profile_background_color":"022330","profile_background_image_url":"http:\/\/a0.twimg.com\/profile_background_images\/388606603\/system-failure-matrix-code-wallpaper.jpg","profile_background_image_url_https":"https:\/\/si0.twimg.com\/profile_background_images\/388606603\/system-failure-matrix-code-wallpaper.jpg","profile_background_tile":true,"profile_image_url":"http:\/\/a0.twimg.com\/profile_images\/1205289753\/photo_normal.jpg","profile_image_url_https":"https:\/\/si0.twimg.com\/profile_images\/1205289753\/photo_normal.jpg","profile_link_color":"0084B4","profile_sidebar_border_color":"A8C7F7","profile_sidebar_fill_color":"C0DFEC","profile_text_color":"333333","profile_use_background_image":true,"default_profile":false,"default_profile_image":false,"following":true,"follow_request_sent":null,"notifications":null},"geo":null,"coordinates":null,"place":null,"contributors":null,"retweet_count":0,"favorite_count":0,"entities":{"hashtags":[{"text":"HHKBSucks","indices":[49,59]}],"symbols":[],"urls":[],"user_mentions":[]},"favorited":false,"retweeted":false,"lang":"zh"},{"created_at":"Tue Jun 25 15:17:47 +0000 2013","id":349546975567413248,"id_str":"349546975567413248","text":"RT @BoA_avex_staff: BoA\u3001\u65b0\u66f2\u30ad\u30e3\u30f3\u30da\u30fc\u30f3\u306e\u5168\u8c8c\u304c\u660e\u3089\u304b\u306b \n (\uff22\uff4f\uff21) \u30cb\u30e5\u30fc\u30b9-ORICON STYLE- http:\/\/t.co\/d3ur0s8TX9","source":"\u003ca href=\"http:\/\/www.tweetdeck.com\" rel=\"nofollow\"\u003eTweetDeck\u003c\/a\u003e","truncated":false,"in_reply_to_status_id":null,"in_reply_to_status_id_str":null,"in_reply_to_user_id":null,"in_reply_to_user_id_str":null,"in_reply_to_screen_name":null,"user":{"id":345776117,"id_str":"345776117","name":"BoA the KOREA \ubcf4\uc544","screen_name":"BoAtheKOREA","location":"Korea","description":"\ubcf4\uc544\ub354\ucf54\ub9ac\uc544(BoAtheKOREA)  \u25cf \uac00\uc218 \ubcf4\uc544 ( @BoAkwon )\ub2d8\uc5d0 \uad00\ud55c \ubaa8\ub4e0 \uc815\ubcf4\ub97c \ud55c\uad6d\uc5b4\ub85c \uc81c\uacf5\ud569\ub2c8\ub2e4","url":null,"entities":{"description":{"urls":[]}},"protected":false,"followers_count":7422,"friends_count":596,"listed_count":67,"created_at":"Sun Jul 31 04:36:46 +0000 2011","favourites_count":1024,"utc_offset":32400,"time_zone":"Seoul","geo_enabled":false,"verified":false,"statuses_count":7688,"lang":"ko","contributors_enabled":false,"is_translator":false,"profile_background_color":"C0DEED","profile_background_image_url":"http:\/\/a0.twimg.com\/profile_background_images\/645819141\/ycz1u82yqr54i0v1g20a.jpeg","profile_background_image_url_https":"https:\/\/si0.twimg.com\/profile_background_images\/645819141\/ycz1u82yqr54i0v1g20a.jpeg","profile_background_tile":false,"profile_image_url":"http:\/\/a0.twimg.com\/profile_images\/2552492290\/ge3nbql5iz9tm74wizsh_normal.jpeg","profile_image_url_https":"https:\/\/si0.twimg.com\/profile_images\/2552492290\/ge3nbql5iz9tm74wizsh_normal.jpeg","profile_link_color":"0084B4","profile_sidebar_border_color":"C0DEED","profile_sidebar_fill_color":"DDEEF6","profile_text_color":"333333","profile_use_background_image":true,"default_profile":false,"default_profile_image":false,"following":true,"follow_request_sent":null,"notifications":null},"geo":null,"coordinates":null,"place":null,"contributors":null,"retweeted_status":{"created_at":"Tue Jun 25 15:16:51 +0000 2013","id":349546738488590338,"id_str":"349546738488590338","text":"BoA\u3001\u65b0\u66f2\u30ad\u30e3\u30f3\u30da\u30fc\u30f3\u306e\u5168\u8c8c\u304c\u660e\u3089\u304b\u306b \n (\uff22\uff4f\uff21) \u30cb\u30e5\u30fc\u30b9-ORICON STYLE- http:\/\/t.co\/d3ur0s8TX9","source":"\u003ca href=\"http:\/\/twitter.com\/tweetbutton\" rel=\"nofollow\"\u003eTweet Button\u003c\/a\u003e","truncated":false,"in_reply_to_status_id":null,"in_reply_to_status_id_str":null,"in_reply_to_user_id":null,"in_reply_to_user_id_str":null,"in_reply_to_screen_name":null,"user":{"id":394544732,"id_str":"394544732","name":"BoA_avex_staff","screen_name":"BoA_avex_staff","location":"","description":"BoA \u30b9\u30bf\u30c3\u30d5\u306b\u3088\u308btwitter\u30a2\u30ab\u30a6\u30f3\u30c8\u3002BoA\u306b\u95a2\u3059\u308b\u60c5\u5831\u3092\u914d\u4fe1\u4e2d\u3002","url":"http:\/\/t.co\/RJ8SYconiS","entities":{"url":{"urls":[{"url":"http:\/\/t.co\/RJ8SYconiS","expanded_url":"http:\/\/www.avexnet.or.jp\/boa\/","display_url":"avexnet.or.jp\/boa\/","indices":[0,22]}]},"description":{"urls":[]}},"protected":false,"followers_count":2698,"friends_count":1027,"listed_count":58,"created_at":"Thu Oct 20 07:35:55 +0000 2011","favourites_count":0,"utc_offset":-36000,"time_zone":"Hawaii","geo_enabled":false,"verified":false,"statuses_count":133,"lang":"ja","contributors_enabled":false,"is_translator":false,"profile_background_color":"C0DEED","profile_background_image_url":"http:\/\/a0.twimg.com\/profile_background_images\/378800000006651449\/469ab5faabdc89ac9b80dd33b812eb8a.png","profile_background_image_url_https":"https:\/\/si0.twimg.com\/profile_background_images\/378800000006651449\/469ab5faabdc89ac9b80dd33b812eb8a.png","profile_background_tile":true,"profile_image_url":"http:\/\/a0.twimg.com\/profile_images\/378800000039296772\/898344a538ec0e358fa35b4851519e97_normal.png","profile_image_url_https":"https:\/\/si0.twimg.com\/profile_images\/378800000039296772\/898344a538ec0e358fa35b4851519e97_normal.png","profile_link_color":"0084B4","profile_sidebar_border_color":"FFFFFF","profile_sidebar_fill_color":"DDEEF6","profile_text_color":"333333","profile_use_background_image":true,"default_profile":false,"default_profile_image":false,"following":null,"follow_request_sent":null,"notifications":null},"geo":null,"coordinates":null,"place":null,"contributors":null,"retweet_count":21,"favorite_count":4,"entities":{"hashtags":[],"symbols":[],"urls":[{"url":"http:\/\/t.co\/d3ur0s8TX9","expanded_url":"http:\/\/bit.ly\/11Y779B","display_url":"bit.ly\/11Y779B","indices":[48,70]}],"user_mentions":[]},"favorited":false,"retweeted":false,"possibly_sensitive":false,"lang":"ja"},"retweet_count":21,"favorite_count":0,"entities":{"hashtags":[],"symbols":[],"urls":[{"url":"http:\/\/t.co\/d3ur0s8TX9","expanded_url":"http:\/\/bit.ly\/11Y779B","display_url":"bit.ly\/11Y779B","indices":[68,90]}],"user_mentions":[{"screen_name":"BoA_avex_staff","name":"BoA_avex_staff","id":394544732,"id_str":"394544732","indices":[3,18]}]},"favorited":false,"retweeted":false,"possibly_sensitive":false,"lang":"ja"},{"created_at":"Tue Jun 25 15:14:27 +0000 2013","id":349546133032411136,"id_str":"349546133032411136","text":"RT @Cloudbleu: \u897f\u5357\u626c\u5927\u603b\u7edf\u4e07\u5c81\uff01RT @laoyang945: \u897f\u5357\u8054\u90a6\u4e07\u5c81 RT @tun_kan: \u9673\u5149\u8aa0\u4e00\u570b\u5169\u5236\u65b0\u89e3\uff1a\u5317\u4eac\u81ea\u5df1\u5708\u8d77\u4f86\u5be6\u65bd\u4e00\u9ee8\u5c08\u5236\uff0c\u5168\u570b\u5176\u5b83\u5404\u7701\u806f\u5408\u5be6\u65bd\u81ea\u7531\u6c11\u4e3b\u5236\u5ea6\u3002","source":"web","truncated":false,"in_reply_to_status_id":null,"in_reply_to_status_id_str":null,"in_reply_to_user_id":null,"in_reply_to_user_id_str":null,"in_reply_to_screen_name":null,"user":{"id":18325616,"id_str":"18325616","name":"akid","screen_name":"akid_","location":"on line","description":"Sometimes tweet in English, \u6709\u65f6\u5220\u5bf9\u8bdd\u63a8\u3002Contact me if you need translating service for company: akidtongtong # gmail","url":"http:\/\/t.co\/RiUr0MduM9","entities":{"url":{"urls":[{"url":"http:\/\/t.co\/RiUr0MduM9","expanded_url":"http:\/\/akidtongtong.tumblr.com\/","display_url":"akidtongtong.tumblr.com","indices":[0,22]}]},"description":{"urls":[]}},"protected":false,"followers_count":4415,"friends_count":750,"listed_count":88,"created_at":"Tue Dec 23 03:46:48 +0000 2008","favourites_count":1345,"utc_offset":-32400,"time_zone":"Alaska","geo_enabled":true,"verified":false,"statuses_count":33233,"lang":"en","contributors_enabled":false,"is_translator":false,"profile_background_color":"FAF2F2","profile_background_image_url":"http:\/\/a0.twimg.com\/profile_background_images\/554468681\/p589736591.jpg","profile_background_image_url_https":"https:\/\/si0.twimg.com\/profile_background_images\/554468681\/p589736591.jpg","profile_background_tile":false,"profile_image_url":"http:\/\/a0.twimg.com\/profile_images\/3662709812\/526429d356c3f3931847568511d4232e_normal.png","profile_image_url_https":"https:\/\/si0.twimg.com\/profile_images\/3662709812\/526429d356c3f3931847568511d4232e_normal.png","profile_banner_url":"https:\/\/pbs.twimg.com\/profile_banners\/18325616\/1364576749","profile_link_color":"E061AB","profile_sidebar_border_color":"FFFFFF","profile_sidebar_fill_color":"79E633","profile_text_color":"3C3940","profile_use_background_image":true,"default_profile":false,"default_profile_image":false,"following":true,"follow_request_sent":null,"notifications":null},"geo":null,"coordinates":null,"place":null,"contributors":null,"retweeted_status":{"created_at":"Tue Jun 25 15:02:05 +0000 2013","id":349543023153123331,"id_str":"349543023153123331","text":"\u897f\u5357\u626c\u5927\u603b\u7edf\u4e07\u5c81\uff01RT @laoyang945: \u897f\u5357\u8054\u90a6\u4e07\u5c81 RT @tun_kan: \u9673\u5149\u8aa0\u4e00\u570b\u5169\u5236\u65b0\u89e3\uff1a\u5317\u4eac\u81ea\u5df1\u5708\u8d77\u4f86\u5be6\u65bd\u4e00\u9ee8\u5c08\u5236\uff0c\u5168\u570b\u5176\u5b83\u5404\u7701\u806f\u5408\u5be6\u65bd\u81ea\u7531\u6c11\u4e3b\u5236\u5ea6\u3002","source":"\u003ca href=\"http:\/\/tapbots.com\/tweetbot\" rel=\"nofollow\"\u003eTweetbot for iOS\u003c\/a\u003e","truncated":false,"in_reply_to_status_id":null,"in_reply_to_status_id_str":null,"in_reply_to_user_id":null,"in_reply_to_user_id_str":null,"in_reply_to_screen_name":null,"user":{"id":48037575,"id_str":"48037575","name":"\u843d\u4e54\u6728","screen_name":"Cloudbleu","location":"","description":"\u7f8e\u98df\u7f8e\u666f\u7f8e\u9152\u7f8e\u4eba\uff0c\u4eba\u751f\u6240\u6709\u8ffd\u6c42\u83ab\u8fc7\u4e8e\u6b64\u3002\u591a\u591a\u732b\u662f\u6700\u840c\u7684\u55b5\uff5e","url":null,"entities":{"description":{"urls":[]}},"protected":false,"followers_count":522,"friends_count":339,"listed_count":12,"created_at":"Wed Jun 17 17:23:17 +0000 2009","favourites_count":26,"utc_offset":28800,"time_zone":"Beijing","geo_enabled":false,"verified":false,"statuses_count":9332,"lang":"en","contributors_enabled":false,"is_translator":false,"profile_background_color":"9AE4E8","profile_background_image_url":"http:\/\/a0.twimg.com\/profile_background_images\/175691541\/582b2db2jw6dbrf19rzbcj.jpg","profile_background_image_url_https":"https:\/\/si0.twimg.com\/profile_background_images\/175691541\/582b2db2jw6dbrf19rzbcj.jpg","profile_background_tile":true,"profile_image_url":"http:\/\/a0.twimg.com\/profile_images\/2453624037\/wgcwzkkbhonjzjrvm2vx_normal.jpeg","profile_image_url_https":"https:\/\/si0.twimg.com\/profile_images\/2453624037\/wgcwzkkbhonjzjrvm2vx_normal.jpeg","profile_banner_url":"https:\/\/pbs.twimg.com\/profile_banners\/48037575\/1350864756","profile_link_color":"0084B4","profile_sidebar_border_color":"BDDCAD","profile_sidebar_fill_color":"DDFFCC","profile_text_color":"333333","profile_use_background_image":true,"default_profile":false,"default_profile_image":false,"following":null,"follow_request_sent":null,"notifications":null},"geo":null,"coordinates":null,"place":null,"contributors":null,"retweet_count":2,"favorite_count":0,"entities":{"hashtags":[],"symbols":[],"urls":[],"user_mentions":[{"screen_name":"laoyang945","name":"\u4f4e\u7aef\u5c0f\u6c14\u7f8a\u5403\u864e","id":50969839,"id_str":"50969839","indices":[12,23]},{"screen_name":"tun_kan","name":"\u502b","id":201188532,"id_str":"201188532","indices":[35,43]}]},"favorited":false,"retweeted":false,"lang":"ja"},"retweet_count":2,"favorite_count":0,"entities":{"hashtags":[],"symbols":[],"urls":[],"user_mentions":[{"screen_name":"Cloudbleu","name":"\u843d\u4e54\u6728","id":48037575,"id_str":"48037575","indices":[3,13]},{"screen_name":"laoyang945","name":"\u4f4e\u7aef\u5c0f\u6c14\u7f8a\u5403\u864e","id":50969839,"id_str":"50969839","indices":[27,38]},{"screen_name":"tun_kan","name":"\u502b","id":201188532,"id_str":"201188532","indices":[50,58]}]},"favorited":false,"retweeted":false,"lang":"ja"},{"created_at":"Tue Jun 25 15:14:05 +0000 2013","id":349546041504317440,"id_str":"349546041504317440","text":"RT @BoA_avex_staff: \u3010BoA\u3011\u5e97\u982dDAY\u3067\u306f\u300cTail's Photo\u300d\u30a4\u30d9\u30f3\u30c8\u306e\u4ed6\u3001\u300cTail of Hope\u300d\u00d7\u300cCatch the Tail of Hope\u300d\u3046\u3061\u308f\u914d\u5e03\u3082\u3054\u3056\u3044\u307e\u3059\uff01\u662f\u975e\u662f\u975e\u30bf\u30ef\u30fc\u30ec\u30b3\u30fc\u30c9\u6e0b\u8c37\u5e97\u306b\u304a\u7acb\u5bc4\u304f\u3060\u3055\u3044\uff01 http:\/\/t.co\u2026","source":"\u003ca href=\"http:\/\/www.tweetdeck.com\" rel=\"nofollow\"\u003eTweetDeck\u003c\/a\u003e","truncated":false,"in_reply_to_status_id":null,"in_reply_to_status_id_str":null,"in_reply_to_user_id":null,"in_reply_to_user_id_str":null,"in_reply_to_screen_name":null,"user":{"id":345776117,"id_str":"345776117","name":"BoA the KOREA \ubcf4\uc544","screen_name":"BoAtheKOREA","location":"Korea","description":"\ubcf4\uc544\ub354\ucf54\ub9ac\uc544(BoAtheKOREA)  \u25cf \uac00\uc218 \ubcf4\uc544 ( @BoAkwon )\ub2d8\uc5d0 \uad00\ud55c \ubaa8\ub4e0 \uc815\ubcf4\ub97c \ud55c\uad6d\uc5b4\ub85c \uc81c\uacf5\ud569\ub2c8\ub2e4","url":null,"entities":{"description":{"urls":[]}},"protected":false,"followers_count":7422,"friends_count":596,"listed_count":67,"created_at":"Sun Jul 31 04:36:46 +0000 2011","favourites_count":1024,"utc_offset":32400,"time_zone":"Seoul","geo_enabled":false,"verified":false,"statuses_count":7688,"lang":"ko","contributors_enabled":false,"is_translator":false,"profile_background_color":"C0DEED","profile_background_image_url":"http:\/\/a0.twimg.com\/profile_background_images\/645819141\/ycz1u82yqr54i0v1g20a.jpeg","profile_background_image_url_https":"https:\/\/si0.twimg.com\/profile_background_images\/645819141\/ycz1u82yqr54i0v1g20a.jpeg","profile_background_tile":false,"profile_image_url":"http:\/\/a0.twimg.com\/profile_images\/2552492290\/ge3nbql5iz9tm74wizsh_normal.jpeg","profile_image_url_https":"https:\/\/si0.twimg.com\/profile_images\/2552492290\/ge3nbql5iz9tm74wizsh_normal.jpeg","profile_link_color":"0084B4","profile_sidebar_border_color":"C0DEED","profile_sidebar_fill_color":"DDEEF6","profile_text_color":"333333","profile_use_background_image":true,"default_profile":false,"default_profile_image":false,"following":true,"follow_request_sent":null,"notifications":null},"geo":null,"coordinates":null,"place":null,"contributors":null,"retweeted_status":{"created_at":"Tue Jun 25 15:13:39 +0000 2013","id":349545933819756545,"id_str":"349545933819756545","text":"\u3010BoA\u3011\u5e97\u982dDAY\u3067\u306f\u300cTail's Photo\u300d\u30a4\u30d9\u30f3\u30c8\u306e\u4ed6\u3001\u300cTail of Hope\u300d\u00d7\u300cCatch the Tail of Hope\u300d\u3046\u3061\u308f\u914d\u5e03\u3082\u3054\u3056\u3044\u307e\u3059\uff01\u662f\u975e\u662f\u975e\u30bf\u30ef\u30fc\u30ec\u30b3\u30fc\u30c9\u6e0b\u8c37\u5e97\u306b\u304a\u7acb\u5bc4\u304f\u3060\u3055\u3044\uff01 http:\/\/t.co\/IN8484E1u6","source":"web","truncated":false,"in_reply_to_status_id":null,"in_reply_to_status_id_str":null,"in_reply_to_user_id":null,"in_reply_to_user_id_str":null,"in_reply_to_screen_name":null,"user":{"id":394544732,"id_str":"394544732","name":"BoA_avex_staff","screen_name":"BoA_avex_staff","location":"","description":"BoA \u30b9\u30bf\u30c3\u30d5\u306b\u3088\u308btwitter\u30a2\u30ab\u30a6\u30f3\u30c8\u3002BoA\u306b\u95a2\u3059\u308b\u60c5\u5831\u3092\u914d\u4fe1\u4e2d\u3002","url":"http:\/\/t.co\/RJ8SYconiS","entities":{"url":{"urls":[{"url":"http:\/\/t.co\/RJ8SYconiS","expanded_url":"http:\/\/www.avexnet.or.jp\/boa\/","display_url":"avexnet.or.jp\/boa\/","indices":[0,22]}]},"description":{"urls":[]}},"protected":false,"followers_count":2698,"friends_count":1027,"listed_count":58,"created_at":"Thu Oct 20 07:35:55 +0000 2011","favourites_count":0,"utc_offset":-36000,"time_zone":"Hawaii","geo_enabled":false,"verified":false,"statuses_count":133,"lang":"ja","contributors_enabled":false,"is_translator":false,"profile_background_color":"C0DEED","profile_background_image_url":"http:\/\/a0.twimg.com\/profile_background_images\/378800000006651449\/469ab5faabdc89ac9b80dd33b812eb8a.png","profile_background_image_url_https":"https:\/\/si0.twimg.com\/profile_background_images\/378800000006651449\/469ab5faabdc89ac9b80dd33b812eb8a.png","profile_background_tile":true,"profile_image_url":"http:\/\/a0.twimg.com\/profile_images\/378800000039296772\/898344a538ec0e358fa35b4851519e97_normal.png","profile_image_url_https":"https:\/\/si0.twimg.com\/profile_images\/378800000039296772\/898344a538ec0e358fa35b4851519e97_normal.png","profile_link_color":"0084B4","profile_sidebar_border_color":"FFFFFF","profile_sidebar_fill_color":"DDEEF6","profile_text_color":"333333","profile_use_background_image":true,"default_profile":false,"default_profile_image":false,"following":null,"follow_request_sent":null,"notifications":null},"geo":null,"coordinates":null,"place":null,"contributors":null,"retweet_count":37,"favorite_count":3,"entities":{"hashtags":[],"symbols":[],"urls":[],"user_mentions":[],"media":[{"id":349545933828145152,"id_str":"349545933828145152","indices":[108,130],"media_url":"http:\/\/pbs.twimg.com\/media\/BNnWLMKCQAAso3S.jpg","media_url_https":"https:\/\/pbs.twimg.com\/media\/BNnWLMKCQAAso3S.jpg","url":"http:\/\/t.co\/IN8484E1u6","display_url":"pic.twitter.com\/IN8484E1u6","expanded_url":"http:\/\/twitter.com\/BoA_avex_staff\/status\/349545933819756545\/photo\/1","type":"photo","sizes":{"medium":{"w":600,"h":600,"resize":"fit"},"large":{"w":640,"h":640,"resize":"fit"},"thumb":{"w":150,"h":150,"resize":"crop"},"small":{"w":340,"h":340,"resize":"fit"}}}]},"favorited":false,"retweeted":false,"possibly_sensitive":false,"lang":"ja"},"retweet_count":37,"favorite_count":0,"entities":{"hashtags":[],"symbols":[],"urls":[],"user_mentions":[{"screen_name":"BoA_avex_staff","name":"BoA_avex_staff","id":394544732,"id_str":"394544732","indices":[3,18]}]},"favorited":false,"retweeted":false,"lang":"ja"},{"created_at":"Tue Jun 25 15:13:53 +0000 2013","id":349545992451923969,"id_str":"349545992451923969","text":"RT @edgar820413:\u54ce\uff01\u522b\u73a9\u5200\u3002RT @oran_ge \u3002\u3002\u3002RT @yunzhenger: touch\u6389\u6c34\u91cc\u6df9\u6b7b\u4e86\u3002\u3002\u3002\u817f\u53d4\u8bf4\u53ef\u4ee5\u628a\u540e\u76d6\u62c6\u4e86\uff0c\u56e0\u4e3a\u4ed6\u9001\u6211\u7684\u65f6\u5019\u4e0a\u9762\u523b\u5b57\u4e86\u3002\u3002\u3002\u7136\u540e\u6211\u5c31\u62c6\u4e86\uff0c\u53cc\u7acb\u4eba\u5254\u8089\u5200\u679c\u7136\u662f\u53c8\u5feb\u53c8\u597d\uff0c\u5207\u8089\u4e0d\u662f\u76d6\u7684\uff0c\uff0c\uff0c\u6211\u53bb\u533b\u9662\u7f1d\u9488\u4e86\uff0c\u540c\u5fd7\u4eec\u3002\u3002\u3002","source":"\u003ca href=\"http:\/\/google.com\" rel=\"nofollow\"\u003enewmyteabot27\u003c\/a\u003e","truncated":false,"in_reply_to_status_id":null,"in_reply_to_status_id_str":null,"in_reply_to_user_id":null,"in_reply_to_user_id_str":null,"in_reply_to_screen_name":null,"user":{"id":267502889,"id_str":"267502889","name":"\u4e2d\u6587\u70ed\u63a8\u673a\u5668\u4eba","screen_name":"iruitui","location":"\u8be5\u5730\u5740\u65e0\u6cd5\u663e\u793a","description":"\u5bfb\u627e\u5e76\u8f6c\u53d1\u70ed\u95e8\u6216\u6709\u8da3\u7684\u63a8\u6587\u3002\r\n\r\n\u6240\u8f6c\u53d1\u63a8\u6587\u5e76\u4e0d\u8868\u660e\u672c\u5e10\u53f7\u7ef4\u62a4\u8005\u89c2\u70b9\u3002\u63a8\u6587\u7684\u771f\u4f2a\u4e0e\u5bf9\u9519\u8bf7\u81ea\u884c\u5224\u65ad\u3002\r\n\r\n\u5982\u6709\u88ab\u672c\u63a8\u8f6c\u53d1\u7684\u63a8\u6587\u9700\u8981\u5220\u9664\uff0c\u8bf7\u77e5\u6089 @iruitui\u3002","url":"https:\/\/t.co\/OTUFpm2Idf","entities":{"url":{"urls":[{"url":"https:\/\/t.co\/OTUFpm2Idf","expanded_url":"https:\/\/www.google.com\/ncr","display_url":"google.com\/ncr","indices":[0,23]}]},"description":{"urls":[]}},"protected":false,"followers_count":3367,"friends_count":1,"listed_count":111,"created_at":"Thu Mar 17 01:57:12 +0000 2011","favourites_count":30,"utc_offset":-32400,"time_zone":"Alaska","geo_enabled":false,"verified":false,"statuses_count":98811,"lang":"zh-cn","contributors_enabled":false,"is_translator":false,"profile_background_color":"C0DEED","profile_background_image_url":"http:\/\/a0.twimg.com\/images\/themes\/theme1\/bg.png","profile_background_image_url_https":"https:\/\/si0.twimg.com\/images\/themes\/theme1\/bg.png","profile_background_tile":false,"profile_image_url":"http:\/\/a0.twimg.com\/profile_images\/2830387364\/ab16e3458fd9dec64a098b1e8c1a26f6_normal.png","profile_image_url_https":"https:\/\/si0.twimg.com\/profile_images\/2830387364\/ab16e3458fd9dec64a098b1e8c1a26f6_normal.png","profile_link_color":"0084B4","profile_sidebar_border_color":"C0DEED","profile_sidebar_fill_color":"DDEEF6","profile_text_color":"333333","profile_use_background_image":true,"default_profile":true,"default_profile_image":false,"following":true,"follow_request_sent":null,"notifications":null},"geo":null,"coordinates":null,"place":null,"contributors":null,"retweet_count":0,"favorite_count":0,"entities":{"hashtags":[],"symbols":[],"urls":[],"user_mentions":[{"screen_name":"edgar820413","name":"Eddy","id":59467506,"id_str":"59467506","indices":[3,15]},{"screen_name":"oran_ge","name":"\u53c8\u9178\u53c8\u723d\u7684\u6a58\u5b50","id":6782882,"id_str":"6782882","indices":[25,33]},{"screen_name":"yunzhenger","name":"\u988d\u5ddd\u9633\u5317","id":52291325,"id_str":"52291325","indices":[40,51]}]},"favorited":false,"retweeted":false,"lang":"zh"},{"created_at":"Tue Jun 25 15:13:52 +0000 2013","id":349545990086336513,"id_str":"349545990086336513","text":"RT @jiagm: http:\/\/t.co\/8We2Xp40TK \u7f51\u6613\u8fd9\u7bc7\u83ab\u540d\u5176\u5999\u7684\u4e13\u9898\uff0c\u6709\u597d\u51e0\u4e2a\u95ee\u9898\u3002\u4ee5\u53f3\u4e0b\u89d2\u7684\u56fe\u4e3a\u4f8b\uff0c\u914d\u56fe\u8bf4\u660e\u8bf4\u662f\u201c\u5728\u4e1c\u4eac\uff0c\u901a\u8fc7\u4e00\u6b3e\u540d\u4e3a\u201c\u94c1\u9053NOW\u201d\u7684\u8f6f\u4ef6\uff0c\u53ef\u4ee5\u5b9e\u65f6\u67e5\u8be2\u5230\u6240\u6709\u8f68\u9053\u4ea4\u901a\u7684\u8fd0\u884c\u60c5\u51b5\u2014\u2014\u8fd0\u884c\u901f\u5ea6\u4ee5\u53ca\u5217\u8f66\u4f4d\u7f6e\u3002\u201d\u3002\u800c\u5b9e\u9645\u4e0a\uff0c\u8fd9\u4e00\u6bb5\u5c31\u6709\u51fa\u73b03\u4e2a\u9519\u8bef\u2026","source":"web","truncated":false,"in_reply_to_status_id":null,"in_reply_to_status_id_str":null,"in_reply_to_user_id":null,"in_reply_to_user_id_str":null,"in_reply_to_screen_name":null,"user":{"id":18325616,"id_str":"18325616","name":"akid","screen_name":"akid_","location":"on line","description":"Sometimes tweet in English, \u6709\u65f6\u5220\u5bf9\u8bdd\u63a8\u3002Contact me if you need translating service for company: akidtongtong # gmail","url":"http:\/\/t.co\/RiUr0MduM9","entities":{"url":{"urls":[{"url":"http:\/\/t.co\/RiUr0MduM9","expanded_url":"http:\/\/akidtongtong.tumblr.com\/","display_url":"akidtongtong.tumblr.com","indices":[0,22]}]},"description":{"urls":[]}},"protected":false,"followers_count":4415,"friends_count":750,"listed_count":88,"created_at":"Tue Dec 23 03:46:48 +0000 2008","favourites_count":1345,"utc_offset":-32400,"time_zone":"Alaska","geo_enabled":true,"verified":false,"statuses_count":33233,"lang":"en","contributors_enabled":false,"is_translator":false,"profile_background_color":"FAF2F2","profile_background_image_url":"http:\/\/a0.twimg.com\/profile_background_images\/554468681\/p589736591.jpg","profile_background_image_url_https":"https:\/\/si0.twimg.com\/profile_background_images\/554468681\/p589736591.jpg","profile_background_tile":false,"profile_image_url":"http:\/\/a0.twimg.com\/profile_images\/3662709812\/526429d356c3f3931847568511d4232e_normal.png","profile_image_url_https":"https:\/\/si0.twimg.com\/profile_images\/3662709812\/526429d356c3f3931847568511d4232e_normal.png","profile_banner_url":"https:\/\/pbs.twimg.com\/profile_banners\/18325616\/1364576749","profile_link_color":"E061AB","profile_sidebar_border_color":"FFFFFF","profile_sidebar_fill_color":"79E633","profile_text_color":"3C3940","profile_use_background_image":true,"default_profile":false,"default_profile_image":false,"following":true,"follow_request_sent":null,"notifications":null},"geo":null,"coordinates":null,"place":null,"contributors":null,"retweeted_status":{"created_at":"Tue Jun 25 15:02:02 +0000 2013","id":349543011258077187,"id_str":"349543011258077187","text":"http:\/\/t.co\/8We2Xp40TK \u7f51\u6613\u8fd9\u7bc7\u83ab\u540d\u5176\u5999\u7684\u4e13\u9898\uff0c\u6709\u597d\u51e0\u4e2a\u95ee\u9898\u3002\u4ee5\u53f3\u4e0b\u89d2\u7684\u56fe\u4e3a\u4f8b\uff0c\u914d\u56fe\u8bf4\u660e\u8bf4\u662f\u201c\u5728\u4e1c\u4eac\uff0c\u901a\u8fc7\u4e00\u6b3e\u540d\u4e3a\u201c\u94c1\u9053NOW\u201d\u7684\u8f6f\u4ef6\uff0c\u53ef\u4ee5\u5b9e\u65f6\u67e5\u8be2\u5230\u6240\u6709\u8f68\u9053\u4ea4\u901a\u7684\u8fd0\u884c\u60c5\u51b5\u2014\u2014\u8fd0\u884c\u901f\u5ea6\u4ee5\u53ca\u5217\u8f66\u4f4d\u7f6e\u3002\u201d\u3002\u800c\u5b9e\u9645\u4e0a\uff0c\u8fd9\u4e00\u6bb5\u5c31\u6709\u51fa\u73b03\u4e2a\u9519\u8bef\u3002\uff08\u63a5\u4e0b\u63a8\uff09","source":"web","truncated":false,"in_reply_to_status_id":null,"in_reply_to_status_id_str":null,"in_reply_to_user_id":null,"in_reply_to_user_id_str":null,"in_reply_to_screen_name":null,"user":{"id":32820821,"id_str":"32820821","name":"Jia Guoming","screen_name":"jiagm","location":"Kobe-shi, Hy\u014dgo, Japan","description":"\uff08\u524d\uff09\u53e3\u888b\u65f6\u4ee3\u7f51\u7ad9\u52a1\u4e3b\u7ba1\u3002\u897f\u5143 1993 \u5e74\uff0c\u4e2d\u534e\u6c11\u56fd\u516b\u5341\u4e8c\u5e74\u751f\u4e8e\u5929\u6d25\u3002\u8f97\u8f6c\u57fc\u7389-\u5317\u4eac-\u4e1c\u4eac-\u57fc\u7389\uff0c\u73b0\u5728\u795e\u6237\u3002SEMC Xperia Z  \/ acro HD. Freedom is not Free. \u65e5\u672c\u8a9e\u30fbSKE\u95a2\u9023\u30c4\u30a4\u30fc\u30c8\u306f\u4e3b\u306b@jia_gm\u3067\u3002SKE48 \u677e\u4e95\u73e0\u7406\u5948\u3055\u3093\u63a8\u3057\u3002\u30ac\u30f3\u30d0\u30ed\u30fc\u3002","url":"http:\/\/t.co\/JbL8ZqOxUg","entities":{"url":{"urls":[{"url":"http:\/\/t.co\/JbL8ZqOxUg","expanded_url":"http:\/\/www.jiagm.me","display_url":"jiagm.me","indices":[0,22]}]},"description":{"urls":[]}},"protected":false,"followers_count":1371,"friends_count":1882,"listed_count":59,"created_at":"Sat Apr 18 07:08:24 +0000 2009","favourites_count":4283,"utc_offset":32400,"time_zone":"Tokyo","geo_enabled":true,"verified":false,"statuses_count":11667,"lang":"zh-cn","contributors_enabled":false,"is_translator":false,"profile_background_color":"0099B9","profile_background_image_url":"http:\/\/a0.twimg.com\/profile_background_images\/72121742\/body_bg_copg.jpg","profile_background_image_url_https":"https:\/\/si0.twimg.com\/profile_background_images\/72121742\/body_bg_copg.jpg","profile_background_tile":false,"profile_image_url":"http:\/\/a0.twimg.com\/profile_images\/593334108\/touxiang_normal.jpg","profile_image_url_https":"https:\/\/si0.twimg.com\/profile_images\/593334108\/touxiang_normal.jpg","profile_banner_url":"https:\/\/pbs.twimg.com\/profile_banners\/32820821\/1355385132","profile_link_color":"0099B9","profile_sidebar_border_color":"5ED4DC","profile_sidebar_fill_color":"95E8EC","profile_text_color":"3C3940","profile_use_background_image":true,"default_profile":false,"default_profile_image":false,"following":null,"follow_request_sent":null,"notifications":null},"geo":null,"coordinates":null,"place":null,"contributors":null,"retweet_count":2,"favorite_count":0,"entities":{"hashtags":[],"symbols":[],"urls":[{"url":"http:\/\/t.co\/8We2Xp40TK","expanded_url":"http:\/\/view.163.com\/special\/reviews\/japantransfer0620.html","display_url":"view.163.com\/special\/review\u2026","indices":[0,22]}],"user_mentions":[]},"favorited":false,"retweeted":false,"possibly_sensitive":false,"lang":"zh"},"retweet_count":2,"favorite_count":0,"entities":{"hashtags":[],"symbols":[],"urls":[{"url":"http:\/\/t.co\/8We2Xp40TK","expanded_url":"http:\/\/view.163.com\/special\/reviews\/japantransfer0620.html","display_url":"view.163.com\/special\/review\u2026","indices":[11,33]}],"user_mentions":[{"screen_name":"jiagm","name":"Jia Guoming","id":32820821,"id_str":"32820821","indices":[3,9]}]},"favorited":false,"retweeted":false,"possibly_sensitive":false,"lang":"zh"},{"created_at":"Tue Jun 25 15:10:09 +0000 2013","id":349545054601359361,"id_str":"349545054601359361","text":"[\uc774\ubca4\ud2b8] \ud558\ub098\ub85c \ub2e4 \ub418\ub294 BoA\uc758 MISSHA \ud2b8\ub9ac\ud50c \ub9bd\uc2a4! \ubdf0\ud2f0\ub137 \uc628\ub77c\uc778\ub2e8\ub3c5\uc73c\ub85c \ubcf4\uc544\uc758 \ud2b8\ub9ac\ud50c \ub9bd\uc2a4 \uad6c\ub9e4 \uc2dc, \ub9bd \ud30c\uc6b0\uce58\ub97c \ub4dc\ub9bd\ub2c8\ub2e4. https:\/\/t.co\/bav9VKLQd4 \ubbf8\uc0e4\ud648\uc5d0\uc11c \uc774\ubca4\ud2b8\ud558\ub124\uc694^^ http:\/\/t.co\/QaLa3Yh1or","source":"\u003ca href=\"http:\/\/www.tweetdeck.com\" rel=\"nofollow\"\u003eTweetDeck\u003c\/a\u003e","truncated":false,"in_reply_to_status_id":null,"in_reply_to_status_id_str":null,"in_reply_to_user_id":null,"in_reply_to_user_id_str":null,"in_reply_to_screen_name":null,"user":{"id":345776117,"id_str":"345776117","name":"BoA the KOREA \ubcf4\uc544","screen_name":"BoAtheKOREA","location":"Korea","description":"\ubcf4\uc544\ub354\ucf54\ub9ac\uc544(BoAtheKOREA)  \u25cf \uac00\uc218 \ubcf4\uc544 ( @BoAkwon )\ub2d8\uc5d0 \uad00\ud55c \ubaa8\ub4e0 \uc815\ubcf4\ub97c \ud55c\uad6d\uc5b4\ub85c \uc81c\uacf5\ud569\ub2c8\ub2e4","url":null,"entities":{"description":{"urls":[]}},"protected":false,"followers_count":7422,"friends_count":596,"listed_count":67,"created_at":"Sun Jul 31 04:36:46 +0000 2011","favourites_count":1024,"utc_offset":32400,"time_zone":"Seoul","geo_enabled":false,"verified":false,"statuses_count":7688,"lang":"ko","contributors_enabled":false,"is_translator":false,"profile_background_color":"C0DEED","profile_background_image_url":"http:\/\/a0.twimg.com\/profile_background_images\/645819141\/ycz1u82yqr54i0v1g20a.jpeg","profile_background_image_url_https":"https:\/\/si0.twimg.com\/profile_background_images\/645819141\/ycz1u82yqr54i0v1g20a.jpeg","profile_background_tile":false,"profile_image_url":"http:\/\/a0.twimg.com\/profile_images\/2552492290\/ge3nbql5iz9tm74wizsh_normal.jpeg","profile_image_url_https":"https:\/\/si0.twimg.com\/profile_images\/2552492290\/ge3nbql5iz9tm74wizsh_normal.jpeg","profile_link_color":"0084B4","profile_sidebar_border_color":"C0DEED","profile_sidebar_fill_color":"DDEEF6","profile_text_color":"333333","profile_use_background_image":true,"default_profile":false,"default_profile_image":false,"following":true,"follow_request_sent":null,"notifications":null},"geo":null,"coordinates":null,"place":null,"contributors":null,"retweet_count":9,"favorite_count":1,"entities":{"hashtags":[],"symbols":[],"urls":[{"url":"https:\/\/t.co\/bav9VKLQd4","expanded_url":"https:\/\/www.facebook.com\/photo.php?fbid=509917229075412","display_url":"facebook.com\/photo.php?fbid\u2026","indices":[77,100]}],"user_mentions":[],"media":[{"id":349545054613942272,"id_str":"349545054613942272","indices":[116,138],"media_url":"http:\/\/pbs.twimg.com\/media\/BNnVYA1CMAAxNE_.jpg","media_url_https":"https:\/\/pbs.twimg.com\/media\/BNnVYA1CMAAxNE_.jpg","url":"http:\/\/t.co\/QaLa3Yh1or","display_url":"pic.twitter.com\/QaLa3Yh1or","expanded_url":"http:\/\/twitter.com\/BoAtheKOREA\/status\/349545054601359361\/photo\/1","type":"photo","sizes":{"large":{"w":403,"h":403,"resize":"fit"},"medium":{"w":403,"h":403,"resize":"fit"},"thumb":{"w":150,"h":150,"resize":"crop"},"small":{"w":340,"h":340,"resize":"fit"}}}]},"favorited":false,"retweeted":false,"possibly_sensitive":false,"lang":"ko"},{"created_at":"Tue Jun 25 15:10:03 +0000 2013","id":349545029221629954,"id_str":"349545029221629954","text":"RT @Sea_Blue:RT @lamkayblog: \u7db2\u53cb\u63d0\u8b70\uff1a\u53bb\u56cd\u6b61\u91cc\u958b\u9e75\u5473\u5e97\uff0c\u62ce\u6b63\u724c\u53eb\u300c\u56cd\u6b61\u91cc\u9e75\u5473\u300d","source":"\u003ca href=\"http:\/\/google.com\" rel=\"nofollow\"\u003enewmyteabot27\u003c\/a\u003e","truncated":false,"in_reply_to_status_id":null,"in_reply_to_status_id_str":null,"in_reply_to_user_id":null,"in_reply_to_user_id_str":null,"in_reply_to_screen_name":null,"user":{"id":267502889,"id_str":"267502889","name":"\u4e2d\u6587\u70ed\u63a8\u673a\u5668\u4eba","screen_name":"iruitui","location":"\u8be5\u5730\u5740\u65e0\u6cd5\u663e\u793a","description":"\u5bfb\u627e\u5e76\u8f6c\u53d1\u70ed\u95e8\u6216\u6709\u8da3\u7684\u63a8\u6587\u3002\r\n\r\n\u6240\u8f6c\u53d1\u63a8\u6587\u5e76\u4e0d\u8868\u660e\u672c\u5e10\u53f7\u7ef4\u62a4\u8005\u89c2\u70b9\u3002\u63a8\u6587\u7684\u771f\u4f2a\u4e0e\u5bf9\u9519\u8bf7\u81ea\u884c\u5224\u65ad\u3002\r\n\r\n\u5982\u6709\u88ab\u672c\u63a8\u8f6c\u53d1\u7684\u63a8\u6587\u9700\u8981\u5220\u9664\uff0c\u8bf7\u77e5\u6089 @iruitui\u3002","url":"https:\/\/t.co\/OTUFpm2Idf","entities":{"url":{"urls":[{"url":"https:\/\/t.co\/OTUFpm2Idf","expanded_url":"https:\/\/www.google.com\/ncr","display_url":"google.com\/ncr","indices":[0,23]}]},"description":{"urls":[]}},"protected":false,"followers_count":3367,"friends_count":1,"listed_count":111,"created_at":"Thu Mar 17 01:57:12 +0000 2011","favourites_count":30,"utc_offset":-32400,"time_zone":"Alaska","geo_enabled":false,"verified":false,"statuses_count":98811,"lang":"zh-cn","contributors_enabled":false,"is_translator":false,"profile_background_color":"C0DEED","profile_background_image_url":"http:\/\/a0.twimg.com\/images\/themes\/theme1\/bg.png","profile_background_image_url_https":"https:\/\/si0.twimg.com\/images\/themes\/theme1\/bg.png","profile_background_tile":false,"profile_image_url":"http:\/\/a0.twimg.com\/profile_images\/2830387364\/ab16e3458fd9dec64a098b1e8c1a26f6_normal.png","profile_image_url_https":"https:\/\/si0.twimg.com\/profile_images\/2830387364\/ab16e3458fd9dec64a098b1e8c1a26f6_normal.png","profile_link_color":"0084B4","profile_sidebar_border_color":"C0DEED","profile_sidebar_fill_color":"DDEEF6","profile_text_color":"333333","profile_use_background_image":true,"default_profile":true,"default_profile_image":false,"following":true,"follow_request_sent":null,"notifications":null},"geo":null,"coordinates":null,"place":null,"contributors":null,"retweet_count":0,"favorite_count":0,"entities":{"hashtags":[],"symbols":[],"urls":[],"user_mentions":[{"screen_name":"Sea_Blue","name":"\u6d77\u85cd","id":21170375,"id_str":"21170375","indices":[3,12]},{"screen_name":"lamkayblog","name":"Kay Lam","id":20854001,"id_str":"20854001","indices":[16,27]}]},"favorited":false,"retweeted":false,"lang":"zh"},{"created_at":"Tue Jun 25 15:06:28 +0000 2013","id":349544124002742272,"id_str":"349544124002742272","text":"Soo boringgg","source":"\u003ca href=\"http:\/\/twitter.com\/download\/iphone\" rel=\"nofollow\"\u003eTwitter for iPhone\u003c\/a\u003e","truncated":false,"in_reply_to_status_id":null,"in_reply_to_status_id_str":null,"in_reply_to_user_id":null,"in_reply_to_user_id_str":null,"in_reply_to_screen_name":null,"user":{"id":230460449,"id_str":"230460449","name":"Ginfentoh","screen_name":"ginfen","location":"malaysia","description":";)","url":null,"entities":{"description":{"urls":[]}},"protected":false,"followers_count":707,"friends_count":163,"listed_count":16,"created_at":"Sat Dec 25 15:09:42 +0000 2010","favourites_count":61,"utc_offset":28800,"time_zone":"Kuala Lumpur","geo_enabled":true,"verified":false,"statuses_count":9571,"lang":"en","contributors_enabled":false,"is_translator":false,"profile_background_color":"CEE5EB","profile_background_image_url":"http:\/\/a0.twimg.com\/profile_background_images\/195907072\/KF64218.jpg","profile_background_image_url_https":"https:\/\/si0.twimg.com\/profile_background_images\/195907072\/KF64218.jpg","profile_background_tile":true,"profile_image_url":"http:\/\/a0.twimg.com\/profile_images\/378800000021429311\/e22260077adeb91646c2e5ef4a61692a_normal.jpeg","profile_image_url_https":"https:\/\/si0.twimg.com\/profile_images\/378800000021429311\/e22260077adeb91646c2e5ef4a61692a_normal.jpeg","profile_banner_url":"https:\/\/pbs.twimg.com\/profile_banners\/230460449\/1368754031","profile_link_color":"CC3366","profile_sidebar_border_color":"E6CAE5","profile_sidebar_fill_color":"FCB0B4","profile_text_color":"333333","profile_use_background_image":true,"default_profile":false,"default_profile_image":false,"following":true,"follow_request_sent":null,"notifications":null},"geo":null,"coordinates":null,"place":null,"contributors":null,"retweet_count":0,"favorite_count":0,"entities":{"hashtags":[],"symbols":[],"urls":[],"user_mentions":[]},"favorited":false,"retweeted":false,"lang":"en"},{"created_at":"Tue Jun 25 15:06:13 +0000 2013","id":349544064120655872,"id_str":"349544064120655872","text":"The latest release of #Firefox proves the Web is the platform for 3D games, video calls and file sharing: http:\/\/t.co\/iTckBsjqBB","source":"\u003ca href=\"http:\/\/www.exacttarget.com\/social\" rel=\"nofollow\"\u003eSocialEngage\u003c\/a\u003e","truncated":false,"in_reply_to_status_id":null,"in_reply_to_status_id_str":null,"in_reply_to_user_id":null,"in_reply_to_user_id_str":null,"in_reply_to_screen_name":null,"user":{"id":2142731,"id_str":"2142731","name":"Firefox","screen_name":"firefox","location":"All over the world","description":"I make the web a little faster, safer, smarter, better.","url":"http:\/\/t.co\/yE4rUZYydZ","entities":{"url":{"urls":[{"url":"http:\/\/t.co\/yE4rUZYydZ","expanded_url":"http:\/\/blog.mozilla.org\/","display_url":"blog.mozilla.org","indices":[0,22]}]},"description":{"urls":[]}},"protected":false,"followers_count":1632769,"friends_count":326292,"listed_count":23913,"created_at":"Sat Mar 24 23:58:14 +0000 2007","favourites_count":1672,"utc_offset":-28800,"time_zone":"Pacific Time (US & Canada)","geo_enabled":false,"verified":true,"statuses_count":7170,"lang":"en","contributors_enabled":false,"is_translator":false,"profile_background_color":"00539F","profile_background_image_url":"http:\/\/a0.twimg.com\/profile_background_images\/803517359\/a9781eb119565e03dc6f15be6e77c5ba.jpeg","profile_background_image_url_https":"https:\/\/si0.twimg.com\/profile_background_images\/803517359\/a9781eb119565e03dc6f15be6e77c5ba.jpeg","profile_background_tile":false,"profile_image_url":"http:\/\/a0.twimg.com\/profile_images\/3302774296\/606a53ef3edfe9633c6f08a4076a5664_normal.png","profile_image_url_https":"https:\/\/si0.twimg.com\/profile_images\/3302774296\/606a53ef3edfe9633c6f08a4076a5664_normal.png","profile_banner_url":"https:\/\/pbs.twimg.com\/profile_banners\/2142731\/1366395406","profile_link_color":"CC3300","profile_sidebar_border_color":"FFFFFF","profile_sidebar_fill_color":"FFFF99","profile_text_color":"333333","profile_use_background_image":true,"default_profile":false,"default_profile_image":false,"following":true,"follow_request_sent":null,"notifications":null},"geo":null,"coordinates":null,"place":null,"contributors":null,"retweet_count":83,"favorite_count":27,"entities":{"hashtags":[{"text":"Firefox","indices":[22,30]}],"symbols":[],"urls":[{"url":"http:\/\/t.co\/iTckBsjqBB","expanded_url":"http:\/\/mzl.la\/18dLgn2","display_url":"mzl.la\/18dLgn2","indices":[106,128]}],"user_mentions":[]},"favorited":false,"retweeted":false,"possibly_sensitive":false,"lang":"en"}]